Workbook

Sheet Intro
B2: Made by: | D2: Grigoryev Vladimir
D3: Karaev Nadir
D4: Varochka Dmitry
D5: Karpushkina Ekaterina
D6: Zakharova Elizaveta
D7: Uskova Olga
D8: Cherniy Nikita
D9: Sharafutdinov Ilia
D10: Kulikov Igor
D11: Smirnova Anastasia
B13: Object of valuation: | D13: Mercedes-Benz Group AG
B15: Methods of valuation: | D15: Income approach
D16: Market approach
B18: Est. price (mln EUR): | D18: =Results!D9*Ratios!D4 -> 64671.515
B19: Est. price per share (EUR): | D19: =Results!D9 -> 67.163014

Sheet Legend
B2: Table of contents:
B17: Legend:
B19: xxx | D19: Assumptions with source
B21: xxx | D21: Analytical assumption
B23: xxx | D23: Change in formula
B25: xxx | D25: Link from other sheet
B27: xxx | D27: Analysis
B29: xxx | D29: Analysis %

Sheet Overview & Results
B2: Main results of preliminary analysis
B4: Sharp profitablity decline
B5: FY2025 marked the sharpest profitability decline since the COVID era. Revenue fell 9.2% year-on-year to €132.2 billion, while EBIT collapsed from €13.6 billion to €5.8 billion — compressing EBIT margin from 9.3% to 4.4%. Net profit dropped 48.8% to €5.3 billion. Three structural headwinds converged simultaneously: US tariff escalation raising cost of sales, a 29% volume decline in China amid intensifying competition from domestic EV players, and €1.6 billion in one-off restructuring charges under the "Next Level Performance" programme launched in April 2025.
B19: Company hold strong in terms of financial endurance
B20: The balance sheet remains solid despite earnings pressure. Total equity stands at €94.2 billion (36.9% of total assets), and operating cash flow of €18.0 billion comfortably covers capital expenditure of €9.7 billion, dividends of €4.3 billion, and share buybacks of €0.4 billion. The group maintains €19.8 billion in liquidity and an undrawn €11 billion syndicated credit facility extended through 2030. Total financial debt of ~€100 billion is structurally elevated but largely attributable to Mercedes-Benz Financial Services — a captive finance arm whose debt is matched by corresponding lease and loan receivables, and should not be conflated with industrial leverage.
B34: Dividends reflect unsertanty
B35: Dividend policy reflects management's commitment to shareholder returns even under stress. The FY2025 dividend of €3.50 per share implies a payout ratio of ~80% — well above the company's stated ~40% target — signalling a deliberate effort to cushion investor sentiment rather than preserve capital. While sustainable in the near term given the cash flow profile, this approach limits balance sheet flexibility if the earnings recovery takes longer than expected.
B46: Main logic implied in valuation
B47: Valuation analysis suggests meaningful upside on a normalised earnings basis. Our weighted blended valuation across six methodologies — Comparables (30%), DCF FCFE (30%), DDM 1-step (15%), DDM H-model (10%), DCF FCFF (10%), and DDM 2-step (5%) — yields an estimated intrinsic value of €67.16 per share, implying 28.7% upside to the current market price. DDM models, which anchor to the dividend stream, converge around €52–59 and broadly confirm the current market price as fair value at depressed earnings. FCFE and FCFF models price in a recovery of EBITDA margins toward 16–17% by 2028, driven by the ramp-up of the new CLA electric platform, the MB.OS software ecosystem, and gradual tariff normalisation — a scenario achievable but not without execution risk.

Sheet Template
F5: Source | G5: UoM | I5: Const | J5: 2021A | K5: 2022A | L5: 2023A | M5: 2024A | N5: 2025A | O5: 2026F | P5: 2027F | Q5: 2028F | R5: 2029F | S5: 2030F
B7: Heading
C9: Subheading
D11: Text

Sheet 1. Core

Sheet BS
A5: Balance sheet | F5: Source | G5: UoM | I5: Const | J5: 2021A | K5: 2022A | L5: 2023A | M5: 2024A | N5: 2025A
B7: Assets
C9: Non-current assets
D11: Intangible assets | F11: Annual statement | G11: =IF(M11="","",IF(AND(M11>=-1,M11<=1), "%","mln EUR")) -> mln EUR | J11: 15005 | K11: 15869 | L11: 17593 | M11: 19436 | N11: 20547
E12: Change YoY | F12: Calcs | G12: =IF(M12="","",IF(AND(M12>=-1,M12<=1), "%","mln EUR")) -> % | K12: =IFERROR(K11/J11-1, "-") -> 0.057580806 | L12: =IFERROR(L11/K11-1, "-") -> 0.10863949 | M12: =IFERROR(M11/L11-1, "-") -> 0.10475757 | N12: =IFERROR(N11/M11-1, "-") -> 0.057161967
G13: =IF(M13="","",IF(AND(M13>=-1,M13<=1), "%","mln EUR"))
D14: Property, plant and equipment including right-of-use assets | F14: Annual statement | G14: =IF(M14="","",IF(AND(M14>=-1,M14<=1), "%","mln EUR")) -> mln EUR | J14: 27859 | K14: 27250 | L14: 26090 | M14: 26537 | N14: 27340
E15: Change YoY | F15: Calcs | G15: =IF(M15="","",IF(AND(M15>=-1,M15<=1), "%","mln EUR")) -> % | K15: =IFERROR(K14/J14-1, "-") -> -0.021860081 | L15: =IFERROR(L14/K14-1, "-") -> -0.042568807 | M15: =IFERROR(M14/L14-1, "-") -> 0.017133001 | N15: =IFERROR(N14/M14-1, "-") -> 0.030259637
G16: =IF(M16="","",IF(AND(M16>=-1,M16<=1), "%","mln EUR"))
D17: Equipment on operating leases | F17: Annual statement | G17: =IF(M17="","",IF(AND(M17>=-1,M17<=1), "%","mln EUR")) -> mln EUR | J17: 44471 | K17: 41552 | L17: 41712 | M17: 45220 | N17: 39472
E18: Change YoY | F18: Calcs | G18: =IF(M18="","",IF(AND(M18>=-1,M18<=1), "%","mln EUR")) -> % | K18: =IFERROR(K17/J17-1, "-") -> -0.065638281 | L18: =IFERROR(L17/K17-1, "-") -> 0.0038505968 | M18: =IFERROR(M17/L17-1, "-") -> 0.084100499 | N18: =IFERROR(N17/M17-1, "-") -> -0.1271119
G19: =IF(M19="","",IF(AND(M19>=-1,M19<=1), "%","mln EUR"))
D20: Equity-method investments | F20: Annual statement | G20: =IF(M20="","",IF(AND(M20>=-1,M20<=1), "%","mln EUR")) -> mln EUR | J20: 13588 | K20: 13530 | L20: 13104 | M20: 12786 | N20: 10037
E21: Change YoY | F21: Calcs | G21: =IF(M21="","",IF(AND(M21>=-1,M21<=1), "%","mln EUR")) -> % | K21: =IFERROR(K20/J20-1, "-") -> -0.0042684722 | L21: =IFERROR(L20/K20-1, "-") -> -0.031485588 | M21: =IFERROR(M20/L20-1, "-") -> -0.024267399 | N21: =IFERROR(N20/M20-1, "-") -> -0.21500078
G22: =IF(M22="","",IF(AND(M22>=-1,M22<=1), "%","mln EUR"))
D23: Receivables from financial services | F23: Annual statement | G23: =IF(M23="","",IF(AND(M23>=-1,M23<=1), "%","mln EUR")) -> mln EUR | J23: 46955 | K23: 48237 | L23: 49742 | M23: 48547 | N23: 41902
E24: Change YoY | F24: Calcs | G24: =IF(M24="","",IF(AND(M24>=-1,M24<=1), "%","mln EUR")) -> % | K24: =IFERROR(K23/J23-1, "-") -> 0.027302737 | L24: =IFERROR(L23/K23-1, "-") -> 0.031200116 | M24: =IFERROR(M23/L23-1, "-") -> -0.024023964 | N24: =IFERROR(N23/M23-1, "-") -> -0.13687766
G25: =IF(M25="","",IF(AND(M25>=-1,M25<=1), "%","mln EUR"))
D26: Marketable debt securities and similar investments | F26: Annual statement | G26: =IF(M26="","",IF(AND(M26>=-1,M26<=1), "%","mln EUR")) -> mln EUR | J26: 873 | K26: 823 | L26: 699 | M26: 644 | N26: 626
E27: Change YoY | F27: Calcs | G27: =IF(M27="","",IF(AND(M27>=-1,M27<=1), "%","mln EUR")) -> % | K27: =IFERROR(K26/J26-1, "-") -> -0.057273769 | L27: =IFERROR(L26/K26-1, "-") -> -0.15066829 | M27: =IFERROR(M26/L26-1, "-") -> -0.078683834 | N27: =IFERROR(N26/M26-1, "-") -> -0.027950311
G28: =IF(M28="","",IF(AND(M28>=-1,M28<=1), "%","mln EUR"))
D29: Other financial assets | F29: Annual statement | G29: =IF(M29="","",IF(AND(M29>=-1,M29<=1), "%","mln EUR")) -> mln EUR | J29: 3181 | K29: 4478 | L29: 4340 | M29: 3020 | N29: 2953
E30: Change YoY | F30: Calcs | G30: =IF(M30="","",IF(AND(M30>=-1,M30<=1), "%","mln EUR")) -> % | K30: =IFERROR(K29/J29-1, "-") -> 0.40773342 | L30: =IFERROR(L29/K29-1, "-") -> -0.030817329 | M30: =IFERROR(M29/L29-1, "-") -> -0.30414747 | N30: =IFERROR(N29/M29-1, "-") -> -0.02218543
G31: =IF(M31="","",IF(AND(M31>=-1,M31<=1), "%","mln EUR"))
D32: Deferred tax assets | F32: Annual statement | G32: =IF(M32="","",IF(AND(M32>=-1,M32<=1), "%","mln EUR")) -> mln EUR | J32: 3434 | K32: 3725 | L32: 4127 | M32: 4335 | N32: 6090
E33: Change YoY | F33: Calcs | G33: =IF(M33="","",IF(AND(M33>=-1,M33<=1), "%","mln EUR")) -> % | K33: =IFERROR(K32/J32-1, "-") -> 0.084740827 | L33: =IFERROR(L32/K32-1, "-") -> 0.10791946 | M33: =IFERROR(M32/L32-1, "-") -> 0.050399806 | N33: =IFERROR(N32/M32-1, "-") -> 0.40484429
G34: =IF(M34="","",IF(AND(M34>=-1,M34<=1), "%","mln EUR"))
D35: Income tax assets | F35: Annual statement | G35: =IF(M35="","",IF(AND(M35>=-1,M35<=1), "%","mln EUR")) -> mln EUR | J35: 0 | K35: 0 | L35: 318 | M35: 327 | N35: 426
E36: Change YoY | F36: Calcs | G36: =IF(M36="","",IF(AND(M36>=-1,M36<=1), "%","mln EUR")) -> % | K36: =IFERROR(K35/J35-1, "-") -> - | L36: =IFERROR(L35/K35-1, "-") -> - | M36: =IFERROR(M35/L35-1, "-") -> 0.028301887 | N36: =IFERROR(N35/M35-1, "-") -> 0.30275229
G37: =IF(M37="","",IF(AND(M37>=-1,M37<=1), "%","mln EUR"))
D38: Other assets | F38: Annual statement | G38: =IF(M38="","",IF(AND(M38>=-1,M38<=1), "%","mln EUR")) -> mln EUR | J38: 1536 | K38: 1677 | L38: 1265 | M38: 2391 | N38: 3941
E39: Change YoY | F39: Calcs | G39: =IF(M39="","",IF(AND(M39>=-1,M39<=1), "%","mln EUR")) -> % | K39: =IFERROR(K38/J38-1, "-") -> 0.091796875 | L39: =IFERROR(L38/K38-1, "-") -> -0.2456768 | M39: =IFERROR(M38/L38-1, "-") -> 0.89011858 | N39: =IFERROR(N38/M38-1, "-") -> 0.64826432
C41: Total non-current assets
D43: Total non-current assets | F43: Calcs | G43: =IF(M43="","",IF(AND(M43>=-1,M43<=1), "%","mln EUR")) -> mln EUR | J43: =SUM(J11,J14,J17,J20,J23,J26,J29,J32,J35,J38,) -> 156902 | K43: =SUM(K11,K14,K17,K20,K23,K26,K29,K32,K35,K38,) -> 157141 | L43: =SUM(L11,L14,L17,L20,L23,L26,L29,L32,L35,L38,) -> 158990 | M43: =SUM(M11,M14,M17,M20,M23,M26,M29,M32,M35,M38,) -> 163243 | N43: =SUM(N11,N14,N17,N20,N23,N26,N29,N32,N35,N38,) -> 153334
E44: Change YoY | F44: Calcs | G44: =IF(M44="","",IF(AND(M44>=-1,M44<=1), "%","mln EUR")) -> % | K44: =IFERROR(K43/J43-1, "-") -> 0.0015232438 | L44: =IFERROR(L43/K43-1, "-") -> 0.011766503 | M44: =IFERROR(M43/L43-1, "-") -> 0.02675011 | N44: =IFERROR(N43/M43-1, "-") -> -0.060700918
C46: Current assets
D48: Inventories | F48: Annual statement | G48: =IF(M48="","",IF(AND(M48>=-1,M48<=1), "%","mln EUR")) -> mln EUR | J48: 21466 | K48: 25621 | L48: 26486 | M48: 26234 | N48: 23933
E49: Change YoY | F49: Calcs | G49: =IF(M49="","",IF(AND(M49>=-1,M49<=1), "%","mln EUR")) -> % | K49: =IFERROR(K48/J48-1, "-") -> 0.19356191 | L49: =IFERROR(L48/K48-1, "-") -> 0.033761368 | M49: =IFERROR(M48/L48-1, "-") -> -0.0095144605 | N49: =IFERROR(N48/M48-1, "-") -> -0.087710605
G50: =IF(M50="","",IF(AND(M50>=-1,M50<=1), "%","mln EUR"))
D51: Trade receivables | F51: Annual statement | G51: =IF(M51="","",IF(AND(M51>=-1,M51<=1), "%","mln EUR")) -> mln EUR | J51: 7673 | K51: 8100 | L51: 7281 | M51: 6973 | N51: 5851
E52: Change YoY | F52: Calcs | G52: =IF(M52="","",IF(AND(M52>=-1,M52<=1), "%","mln EUR")) -> % | K52: =IFERROR(K51/J51-1, "-") -> 0.055649681 | L52: =IFERROR(L51/K51-1, "-") -> -0.10111111 | M52: =IFERROR(M51/L51-1, "-") -> -0.042301882 | N52: =IFERROR(N51/M51-1, "-") -> -0.16090635
G53: =IF(M53="","",IF(AND(M53>=-1,M53<=1), "%","mln EUR"))
D54: Receivables from financial services | F54: Annual statement | G54: =IF(M54="","",IF(AND(M54>=-1,M54<=1), "%","mln EUR")) -> mln EUR | J54: 33670 | K54: 37312 | L54: 39277 | M54: 39320 | N54: 34387
E55: Change YoY | F55: Calcs | G55: =IF(M55="","",IF(AND(M55>=-1,M55<=1), "%","mln EUR")) -> % | K55: =IFERROR(K54/J54-1, "-") -> 0.10816751 | L55: =IFERROR(L54/K54-1, "-") -> 0.052664022 | M55: =IFERROR(M54/L54-1, "-") -> 0.0010947883 | N55: =IFERROR(N54/M54-1, "-") -> -0.12545778
G56: =IF(M56="","",IF(AND(M56>=-1,M56<=1), "%","mln EUR"))
D57: Cash and cash equivalents | F57: Annual statement | G57: =IF(M57="","",IF(AND(M57>=-1,M57<=1), "%","mln EUR")) -> mln EUR | J57: 23120 | K57: 17679 | L57: 15962 | M57: 14511 | N57: 12254
E58: Change YoY | F58: Calcs | G58: =IF(M58="","",IF(AND(M58>=-1,M58<=1), "%","mln EUR")) -> % | K58: =IFERROR(K57/J57-1, "-") -> -0.23533737 | L58: =IFERROR(L57/K57-1, "-") -> -0.097120878 | M58: =IFERROR(M57/L57-1, "-") -> -0.090903396 | N58: =IFERROR(N57/M57-1, "-") -> -0.15553718
G59: =IF(M59="","",IF(AND(M59>=-1,M59<=1), "%","mln EUR"))
D60: Marketable debt securities and similar investments | F60: Annual statement | G60: =IF(M60="","",IF(AND(M60>=-1,M60<=1), "%","mln EUR")) -> mln EUR | J60: 6706 | K60: 6237 | L60: 6159 | M60: 7086 | N60: 6940
E61: Change YoY | F61: Calcs | G61: =IF(M61="","",IF(AND(M61>=-1,M61<=1), "%","mln EUR")) -> % | K61: =IFERROR(K60/J60-1, "-") -> -0.06993737 | L61: =IFERROR(L60/K60-1, "-") -> -0.012506013 | M61: =IFERROR(M60/L60-1, "-") -> 0.15051145 | N61: =IFERROR(N60/M60-1, "-") -> -0.020604008
G62: =IF(M62="","",IF(AND(M62>=-1,M62<=1), "%","mln EUR"))
D63: Other financial assets | F63: Annual statement | G63: =IF(M63="","",IF(AND(M63>=-1,M63<=1), "%","mln EUR")) -> mln EUR | J63: 3079 | K63: 3453 | L63: 3599 | M63: 2868 | N63: 2852
E64: Change YoY | F64: Calcs | G64: =IF(M64="","",IF(AND(M64>=-1,M64<=1), "%","mln EUR")) -> % | K64: =IFERROR(K63/J63-1, "-") -> 0.12146801 | L64: =IFERROR(L63/K63-1, "-") -> 0.042282074 | M64: =IFERROR(M63/L63-1, "-") -> -0.20311198 | N64: =IFERROR(N63/M63-1, "-") -> -0.0055788006
G65: =IF(M65="","",IF(AND(M65>=-1,M65<=1), "%","mln EUR"))
D66: Income tax assets | F66: Annual statement | G66: =IF(M66="","",IF(AND(M66>=-1,M66<=1), "%","mln EUR")) -> mln EUR | J66: 0 | K66: 0 | L66: 798 | M66: 1034 | N66: 1257
E67: Change YoY | F67: Calcs | G67: =IF(M67="","",IF(AND(M67>=-1,M67<=1), "%","mln EUR")) -> % | K67: =IFERROR(K66/J66-1, "-") -> - | L67: =IFERROR(L66/K66-1, "-") -> - | M67: =IFERROR(M66/L66-1, "-") -> 0.29573935 | N67: =IFERROR(N66/M66-1, "-") -> 0.21566731
G68: =IF(M68="","",IF(AND(M68>=-1,M68<=1), "%","mln EUR"))
D69: Other assets | F69: Annual statement | G69: =IF(M69="","",IF(AND(M69>=-1,M69<=1), "%","mln EUR")) -> mln EUR | J69: 4073 | K69: 4472 | L69: 3675 | M69: 3581 | N69: 3645
E70: Change YoY | F70: Calcs | G70: =IF(M70="","",IF(AND(M70>=-1,M70<=1), "%","mln EUR")) -> % | K70: =IFERROR(K69/J69-1, "-") -> 0.09796219 | L70: =IFERROR(L69/K69-1, "-") -> -0.17822004 | M70: =IFERROR(M69/L69-1, "-") -> -0.025578231 | N70: =IFERROR(N69/M69-1, "-") -> 0.017872103
G71: =IF(M71="","",IF(AND(M71>=-1,M71<=1), "%","mln EUR"))
D72: Assets held for sale | F72: Annual statement | G72: =IF(M72="","",IF(AND(M72>=-1,M72<=1), "%","mln EUR")) -> mln EUR | J72: 3142 | K72: 0 | L72: 795 | M72: 160 | N72: 11013
E73: Change YoY | F73: Calcs | G73: =IF(M73="","",IF(AND(M73>=-1,M73<=1), "%","mln EUR")) -> % | K73: =IFERROR(K72/J72-1, "-") -> -1 | L73: =IFERROR(L72/K72-1, "-") -> - | M73: =IFERROR(M72/L72-1, "-") -> -0.79874214 | N73: =IFERROR(N72/M72-1, "-") -> 67.83125
C75: Total current assets
D77: Total current assets | F77: Calcs | G77: =IF(M77="","",IF(AND(M77>=-1,M77<=1), "%","mln EUR")) -> mln EUR | J77: =SUM(J48,J51,J54,J57,J60,J63,J66,J69,J72,) -> 102929 | K77: =SUM(K48,K51,K54,K57,K60,K63,K66,K69,K72,) -> 102874 | L77: =SUM(L48,L51,L54,L57,L60,L63,L66,L69,L72,) -> 104032 | M77: =SUM(M48,M51,M54,M57,M60,M63,M66,M69,M72,) -> 101767 | N77: =SUM(N48,N51,N54,N57,N60,N63,N66,N69,N72,) -> 102132
E78: Change YoY | F78: Calcs | G78: =IF(M78="","",IF(AND(M78>=-1,M78<=1), "%","mln EUR")) -> % | K78: =IFERROR(K77/J77-1, "-") -> -0.00053434892 | L78: =IFERROR(L77/K77-1, "-") -> 0.011256489 | M78: =IFERROR(M77/L77-1, "-") -> -0.021772147 | N78: =IFERROR(N77/M77-1, "-") -> 0.0035866243
C80: Total assets
D82: Total assets | F82: Calcs | G82: =IF(M82="","",IF(AND(M82>=-1,M82<=1), "%","mln EUR")) -> mln EUR | J82: =SUM(J43,J77,) -> 259831 | K82: =SUM(K43,K77,) -> 260015 | L82: =SUM(L43,L77,) -> 263022 | M82: =SUM(M43,M77,) -> 265010 | N82: =SUM(N43,N77,) -> 255466
E83: Change YoY | F83: Calcs | G83: =IF(M83="","",IF(AND(M83>=-1,M83<=1), "%","mln EUR")) -> % | K83: =IFERROR(K82/J82-1, "-") -> 0.00070815261 | L83: =IFERROR(L82/K82-1, "-") -> 0.011564717 | M83: =IFERROR(M82/L82-1, "-") -> 0.0075583031 | N83: =IFERROR(N82/M82-1, "-") -> -0.036013735
B85: Liabilities
C87: Non-current liabilities
D89: Provisions for pensions and similar obligations | F89: Annual statement | G89: =IF(M89="","",IF(AND(M89>=-1,M89<=1), "%","mln EUR")) -> mln EUR | J89: 5359 | K89: 1021 | L89: 1090 | M89: 952 | N89: 807
E90: Change YoY | F90: Calcs | G90: =IF(M90="","",IF(AND(M90>=-1,M90<=1), "%","mln EUR")) -> % | K90: =IFERROR(K89/J89-1, "-") -> -0.80947938 | L90: =IFERROR(L89/K89-1, "-") -> 0.067580803 | M90: =IFERROR(M89/L89-1, "-") -> -0.1266055 | N90: =IFERROR(N89/M89-1, "-") -> -0.15231092
G91: =IF(M91="","",IF(AND(M91>=-1,M91<=1), "%","mln EUR"))
D92: Provisions for other risks | F92: Annual statement | G92: =IF(M92="","",IF(AND(M92>=-1,M92<=1), "%","mln EUR")) -> mln EUR | J92: 7909 | K92: 6438 | L92: 7345 | M92: 7332 | N92: 7612
E93: Change YoY | F93: Calcs | G93: =IF(M93="","",IF(AND(M93>=-1,M93<=1), "%","mln EUR")) -> % | K93: =IFERROR(K92/J92-1, "-") -> -0.18599064 | L93: =IFERROR(L92/K92-1, "-") -> 0.14088226 | M93: =IFERROR(M92/L92-1, "-") -> -0.0017699115 | N93: =IFERROR(N92/M92-1, "-") -> 0.038188762
G94: =IF(M94="","",IF(AND(M94>=-1,M94<=1), "%","mln EUR"))
D95: Financing liabilities | F95: Annual statement | G95: =IF(M95="","",IF(AND(M95>=-1,M95<=1), "%","mln EUR")) -> mln EUR | J95: 73543 | K95: 62051 | L95: 63724 | M95: 73487 | N95: 62410
E96: Change YoY | F96: Calcs | G96: =IF(M96="","",IF(AND(M96>=-1,M96<=1), "%","mln EUR")) -> % | K96: =IFERROR(K95/J95-1, "-") -> -0.15626232 | L96: =IFERROR(L95/K95-1, "-") -> 0.026961693 | M96: =IFERROR(M95/L95-1, "-") -> 0.15320758 | N96: =IFERROR(N95/M95-1, "-") -> -0.15073414
G97: =IF(M97="","",IF(AND(M97>=-1,M97<=1), "%","mln EUR"))
D98: Other financial liabilities | F98: Annual statement | G98: =IF(M98="","",IF(AND(M98>=-1,M98<=1), "%","mln EUR")) -> mln EUR | J98: 1808 | K98: 2524 | L98: 1642 | M98: 1490 | N98: 1278
E99: Change YoY | F99: Calcs | G99: =IF(M99="","",IF(AND(M99>=-1,M99<=1), "%","mln EUR")) -> % | K99: =IFERROR(K98/J98-1, "-") -> 0.3960177 | L99: =IFERROR(L98/K98-1, "-") -> -0.34944532 | M99: =IFERROR(M98/L98-1, "-") -> -0.092570037 | N99: =IFERROR(N98/M98-1, "-") -> -0.14228188
G100: =IF(M100="","",IF(AND(M100>=-1,M100<=1), "%","mln EUR"))
D101: Deferred tax liabilities | F101: Annual statement | G101: =IF(M101="","",IF(AND(M101>=-1,M101<=1), "%","mln EUR")) -> mln EUR | J101: 4488 | K101: 6910 | L101: 7714 | M101: 7497 | N101: 10201
E102: Change YoY | F102: Calcs | G102: =IF(M102="","",IF(AND(M102>=-1,M102<=1), "%","mln EUR")) -> % | K102: =IFERROR(K101/J101-1, "-") -> 0.53966132 | L102: =IFERROR(L101/K101-1, "-") -> 0.11635311 | M102: =IFERROR(M101/L101-1, "-") -> -0.028130672 | N102: =IFERROR(N101/M101-1, "-") -> 0.3606776
G103: =IF(M103="","",IF(AND(M103>=-1,M103<=1), "%","mln EUR"))
D104: Deffered income | F104: Annual statement | G104: =IF(M104="","",IF(AND(M104>=-1,M104<=1), "%","mln EUR")) -> % | J104: 1175 | K104: 1234 | L104: 0 | M104: 0
E105: Change YoY | F105: Calcs | G105: =IF(M105="","",IF(AND(M105>=-1,M105<=1), "%","mln EUR")) -> mln EUR | K105: =IFERROR(K104/J104-1, "-") -> 0.050212766 | L105: =IFERROR(L104/K104-1, "-") -> -1 | M105: =IFERROR(M104/L104-1, "-") -> - | N105: =IFERROR(N104/M104-1, "-") -> -
G106: =IF(M106="","",IF(AND(M106>=-1,M106<=1), "%","mln EUR"))
D107: Contract and refund liabilities | F107: Annual statement | G107: =IF(M107="","",IF(AND(M107>=-1,M107<=1), "%","mln EUR")) -> mln EUR | J107: 3980 | K107: 3656 | L107: 2658 | M107: 3100 | N107: 2942
E108: Change YoY | F108: Calcs | G108: =IF(M108="","",IF(AND(M108>=-1,M108<=1), "%","mln EUR")) -> % | K108: =IFERROR(K107/J107-1, "-") -> -0.081407035 | L108: =IFERROR(L107/K107-1, "-") -> -0.27297593 | M108: =IFERROR(M107/L107-1, "-") -> 0.16629044 | N108: =IFERROR(N107/M107-1, "-") -> -0.050967742
G109: =IF(M109="","",IF(AND(M109>=-1,M109<=1), "%","mln EUR"))
D110: Income tax liabilities | F110: Annual statement | G110: =IF(M110="","",IF(AND(M110>=-1,M110<=1), "%","mln EUR")) -> mln EUR | J110: 0 | K110: 0 | L110: 1473 | M110: 1342 | N110: 1020
E111: Change YoY | F111: Calcs | G111: =IF(M111="","",IF(AND(M111>=-1,M111<=1), "%","mln EUR")) -> % | K111: =IFERROR(K110/J110-1, "-") -> - | L111: =IFERROR(L110/K110-1, "-") -> - | M111: =IFERROR(M110/L110-1, "-") -> -0.088934148 | N111: =IFERROR(N110/M110-1, "-") -> -0.23994039
G112: =IF(M112="","",IF(AND(M112>=-1,M112<=1), "%","mln EUR"))
D113: Other liabilities | F113: Annual statement | G113: =IF(M113="","",IF(AND(M113>=-1,M113<=1), "%","mln EUR")) -> mln EUR | J113: 727 | K113: 1238 | L113: 1270 | M113: 1354 | N113: 1188
E114: Change YoY | F114: Calcs | G114: =IF(M114="","",IF(AND(M114>=-1,M114<=1), "%","mln EUR")) -> % | K114: =IFERROR(K113/J113-1, "-") -> 0.70288858 | L114: =IFERROR(L113/K113-1, "-") -> 0.025848142 | M114: =IFERROR(M113/L113-1, "-") -> 0.066141732 | N114: =IFERROR(N113/M113-1, "-") -> -0.1225997
G115: =IF(M115="","",IF(AND(M115>=-1,M115<=1), "%","mln EUR"))
C116: Total non-current liabilities | G116: =IF(M116="","",IF(AND(M116>=-1,M116<=1), "%","mln EUR"))
G117: =IF(M117="","",IF(AND(M117>=-1,M117<=1), "%","mln EUR"))
D118: Total non-current liabilities | F118: Calcs | G118: =IF(M118="","",IF(AND(M118>=-1,M118<=1), "%","mln EUR")) -> mln EUR | J118: =SUM(J89,J92,J95,J98,J101,J104,J107,J110,J113,) -> 98989 | K118: =SUM(K89,K92,K95,K98,K101,K104,K107,K110,K113,) -> 85072 | L118: =SUM(L89,L92,L95,L98,L101,L104,L107,L110,L113,) -> 86916 | M118: =SUM(M89,M92,M95,M98,M101,M104,M107,M110,M113,) -> 96554 | N118: =SUM(N89,N92,N95,N98,N101,N104,N107,N110,N113,) -> 87458
...

Sheet PL
A5: Income statement (P&L) | F5: Source | G5: UoM | I5: Const | J5: 2021A | K5: 2022A | L5: 2023A | M5: 2024A | N5: 2025A
B7: Income statement
C9: Income statement
D11: Revenue | F11: Annual statement | G11: =IF(M11="","",IF(AND(M11>=-1,M11<=1), "%","mln EUR")) -> mln EUR | J11: 133893 | K11: 150017 | L11: 152390 | M11: 145594 | N11: 132214
E12: Change YoY | F12: Calcs | G12: =IF(M12="","",IF(AND(M12>=-1,M12<=1), "%","mln EUR")) -> % | K12: =IFERROR(K11/J11-1, "-") -> 0.12042452 | L12: =IFERROR(L11/K11-1, "-") -> 0.015818207 | M12: =IFERROR(M11/L11-1, "-") -> -0.044596102 | N12: =IFERROR(N11/M11-1, "-") -> -0.091899391
G13: =IF(M13="","",IF(AND(M13>=-1,M13<=1), "%","mln EUR"))
D14: Cost of goods sold | F14: Annual statement | G14: =IF(M14="","",IF(AND(M14>=-1,M14<=1), "%","mln EUR")) -> mln EUR | J14: -103218 | K14: -115997 | L14: -117386 | M14: -117018 | N14: -109881
E15: Change YoY | F15: Calcs | G15: =IF(M15="","",IF(AND(M15>=-1,M15<=1), "%","mln EUR")) -> % | K15: =IFERROR(K14/J14-1, "-") -> 0.12380593 | L15: =IFERROR(L14/K14-1, "-") -> 0.011974448 | M15: =IFERROR(M14/L14-1, "-") -> -0.0031349565 | N15: =IFERROR(N14/M14-1, "-") -> -0.060990617
G16: =IF(M16="","",IF(AND(M16>=-1,M16<=1), "%","mln EUR"))
D17: Gross profit | F17: Annual statement | G17: =IF(M17="","",IF(AND(M17>=-1,M17<=1), "%","mln EUR")) -> mln EUR | J17: 30675 | K17: 34020 | L17: 35004 | M17: 28576 | N17: 22333
E18: Change YoY | F18: Calcs | G18: =IF(M18="","",IF(AND(M18>=-1,M18<=1), "%","mln EUR")) -> % | K18: =IFERROR(K17/J17-1, "-") -> 0.10904645 | L18: =IFERROR(L17/K17-1, "-") -> 0.028924162 | M18: =IFERROR(M17/L17-1, "-") -> -0.18363616 | N18: =IFERROR(N17/M17-1, "-") -> -0.21847004
E19: Margin | F19: Calcs | G19: =IF(M19="","",IF(AND(M19>=-1,M19<=1), "%","mln EUR")) -> % | J19: =IFERROR(J17/J11, "-") -> 0.22910085 | K19: =IFERROR(K17/K11, "-") -> 0.2267743 | L19: =IFERROR(L17/L11, "-") -> 0.22970011 | M19: =IFERROR(M17/M11, "-") -> 0.19627182 | N19: =IFERROR(N17/N11, "-") -> 0.16891555
G20: =IF(M20="","",IF(AND(M20>=-1,M20<=1), "%","mln EUR"))
D21: Selling expenses | F21: Annual statement | G21: =IF(M21="","",IF(AND(M21>=-1,M21<=1), "%","mln EUR")) -> mln EUR | J21: -9194 | K21: -9482 | L21: -10270 | M21: -9993 | N21: -9718
E22: Change YoY | F22: Calcs | G22: =IF(M22="","",IF(AND(M22>=-1,M22<=1), "%","mln EUR")) -> % | K22: =IFERROR(K21/J21-1, "-") -> 0.031324777 | L22: =IFERROR(L21/K21-1, "-") -> 0.08310483 | M22: =IFERROR(M21/L21-1, "-") -> -0.026971762 | N22: =IFERROR(N21/M21-1, "-") -> -0.027519263
G23: =IF(M23="","",IF(AND(M23>=-1,M23<=1), "%","mln EUR"))
D24: General administrative expenses | F24: Annual statement | G24: =IF(M24="","",IF(AND(M24>=-1,M24<=1), "%","mln EUR")) -> mln EUR | J24: -2808 | K24: -2584 | L24: -2771 | M24: -2529 | N24: -2477
E25: Change YoY | F25: Calcs | G25: =IF(M25="","",IF(AND(M25>=-1,M25<=1), "%","mln EUR")) -> % | K25: =IFERROR(K24/J24-1, "-") -> -0.07977208 | L25: =IFERROR(L24/K24-1, "-") -> 0.072368421 | M25: =IFERROR(M24/L24-1, "-") -> -0.087333093 | N25: =IFERROR(N24/M24-1, "-") -> -0.020561487
G26: =IF(M26="","",IF(AND(M26>=-1,M26<=1), "%","mln EUR"))
D27: Research and non-capitalized development costs | F27: Annual statement | G27: =IF(M27="","",IF(AND(M27>=-1,M27<=1), "%","mln EUR")) -> mln EUR | J27: -5467 | K27: -5602 | L27: -6230 | M27: -5580 | N27: -6055
E28: Change YoY | F28: Calcs | G28: =IF(M28="","",IF(AND(M28>=-1,M28<=1), "%","mln EUR")) -> % | K28: =IFERROR(K27/J27-1, "-") -> 0.024693616 | L28: =IFERROR(L27/K27-1, "-") -> 0.11210282 | M28: =IFERROR(M27/L27-1, "-") -> -0.10433387 | N28: =IFERROR(N27/M27-1, "-") -> 0.085125448
G29: =IF(M29="","",IF(AND(M29>=-1,M29<=1), "%","mln EUR"))
D30: Other operating income/expense | F30: Annual statement | G30: =IF(M30="","",IF(AND(M30>=-1,M30<=1), "%","mln EUR")) -> mln EUR | J30: 1153 | K30: 2034 | L30: 1690 | M30: 2024 | N30: 526
E31: Change YoY | F31: Calcs | G31: =IF(M31="","",IF(AND(M31>=-1,M31<=1), "%","mln EUR")) -> % | K31: =IFERROR(K30/J30-1, "-") -> 0.76409367 | L31: =IFERROR(L30/K30-1, "-") -> -0.16912488 | M31: =IFERROR(M30/L30-1, "-") -> 0.19763314 | N31: =IFERROR(N30/M30-1, "-") -> -0.74011858
G32: =IF(M32="","",IF(AND(M32>=-1,M32<=1), "%","mln EUR"))
D33: Gains/losses on equity-method invesments, net | F33: Annual statement | G33: =IF(M33="","",IF(AND(M33>=-1,M33<=1), "%","mln EUR")) -> mln EUR | J33: 1352 | K33: 1732 | L33: 2129 | M33: 1138 | N33: 1118
E34: Change YoY | F34: Calcs | G34: =IF(M34="","",IF(AND(M34>=-1,M34<=1), "%","mln EUR")) -> % | K34: =IFERROR(K33/J33-1, "-") -> 0.28106509 | L34: =IFERROR(L33/K33-1, "-") -> 0.22921478 | M34: =IFERROR(M33/L33-1, "-") -> -0.46547675 | N34: =IFERROR(N33/M33-1, "-") -> -0.017574692
G35: =IF(M35="","",IF(AND(M35>=-1,M35<=1), "%","mln EUR"))
D36: Other financial income/expense, net | F36: Annual statement | G36: =IF(M36="","",IF(AND(M36>=-1,M36<=1), "%","mln EUR")) -> mln EUR | J36: 317 | K36: 340 | L36: 108 | M36: -37 | N36: 93
E37: Change YoY | F37: Calcs | G37: =IF(M37="","",IF(AND(M37>=-1,M37<=1), "%","mln EUR")) -> mln EUR | K37: =IFERROR(K36/J36-1, "-") -> 0.072555205 | L37: =IFERROR(L36/K36-1, "-") -> -0.68235294 | M37: =IFERROR(M36/L36-1, "-") -> -1.3425926 | N37: =IFERROR(N36/M36-1, "-") -> -3.5135135
G38: =IF(M38="","",IF(AND(M38>=-1,M38<=1), "%","mln EUR"))
D39: EBIT | F39: Annual statement | G39: =IF(M39="","",IF(AND(M39>=-1,M39<=1), "%","mln EUR")) -> mln EUR | J39: 16028 | K39: 20458 | L39: 19660 | M39: 13599 | N39: 5820
E40: Change YoY | F40: Calcs | G40: =IF(M40="","",IF(AND(M40>=-1,M40<=1), "%","mln EUR")) -> % | K40: =IFERROR(K39/J39-1, "-") -> 0.27639132 | L40: =IFERROR(L39/K39-1, "-") -> -0.039006746 | M40: =IFERROR(M39/L39-1, "-") -> -0.30829095 | N40: =IFERROR(N39/M39-1, "-") -> -0.57202735
E41: Margin | F41: Calcs | G41: =IF(M41="","",IF(AND(M41>=-1,M41<=1), "%","mln EUR")) -> % | J41: =IFERROR(J39/J11, "-") -> 0.11970753 | K41: =IFERROR(K39/K11, "-") -> 0.13637121 | L41: =IFERROR(L39/L11, "-") -> 0.12901109 | M41: =IFERROR(M39/M11, "-") -> 0.093403574 | N41: =IFERROR(N39/N11, "-") -> 0.044019544
G42: =IF(M42="","",IF(AND(M42>=-1,M42<=1), "%","mln EUR"))
D43: Interest income | F43: Annual statement | G43: =IF(M43="","",IF(AND(M43>=-1,M43<=1), "%","mln EUR")) -> mln EUR | J43: -217 | K43: -154 | L43: 424 | M43: 548 | N43: 464
E44: Change YoY | F44: Calcs | G44: =IF(M44="","",IF(AND(M44>=-1,M44<=1), "%","mln EUR")) -> % | K44: =IFERROR(K43/J43-1, "-") -> -0.29032258 | L44: =IFERROR(L43/K43-1, "-") -> -3.7532468 | M44: =IFERROR(M43/L43-1, "-") -> 0.29245283 | N44: =IFERROR(N43/M43-1, "-") -> -0.15328467
G45: =IF(M45="","",IF(AND(M45>=-1,M45<=1), "%","mln EUR"))
D46: Profit before income taxes | F46: Annual statement | G46: =IF(M46="","",IF(AND(M46>=-1,M46<=1), "%","mln EUR")) -> mln EUR | J46: 15811 | K46: 20304 | L46: 20084 | M46: 14147 | N46: 6284
E47: Change YoY | F47: Calcs | G47: =IF(M47="","",IF(AND(M47>=-1,M47<=1), "%","mln EUR")) -> % | K47: =IFERROR(K46/J46-1, "-") -> 0.28416925 | L47: =IFERROR(L46/K46-1, "-") -> -0.010835303 | M47: =IFERROR(M46/L46-1, "-") -> -0.29560844 | N47: =IFERROR(N46/M46-1, "-") -> -0.55580688
G48: =IF(M48="","",IF(AND(M48>=-1,M48<=1), "%","mln EUR"))
D49: Income taxes | F49: Annual statement | G49: =IF(M49="","",IF(AND(M49>=-1,M49<=1), "%","mln EUR")) -> mln EUR | J49: -4761 | K49: -5495 | L49: -5553 | M49: -3738 | N49: -953
E50: Change YoY | F50: Calcs | G50: =IF(M50="","",IF(AND(M50>=-1,M50<=1), "%","mln EUR")) -> % | K50: =IFERROR(K49/J49-1, "-") -> 0.15416929 | L50: =IFERROR(L49/K49-1, "-") -> 0.01055505 | M50: =IFERROR(M49/L49-1, "-") -> -0.32685035 | N50: =IFERROR(N49/M49-1, "-") -> -0.74505083
G51: =IF(M51="","",IF(AND(M51>=-1,M51<=1), "%","mln EUR"))
D52: Net profit | F52: Annual statement | G52: =IF(M52="","",IF(AND(M52>=-1,M52<=1), "%","mln EUR")) -> mln EUR | J52: 23396 | K52: 14809 | L52: 14531 | M52: 10409 | N52: 5331
E53: Change YoY | F53: Calcs | G53: =IF(M53="","",IF(AND(M53>=-1,M53<=1), "%","mln EUR")) -> % | K53: =IFERROR(K52/J52-1, "-") -> -0.36702855 | L53: =IFERROR(L52/K52-1, "-") -> -0.018772368 | M53: =IFERROR(M52/L52-1, "-") -> -0.2836694 | N53: =IFERROR(N52/M52-1, "-") -> -0.48784706
E54: Margin | F54: Calcs | G54: =IF(M54="","",IF(AND(M54>=-1,M54<=1), "%","mln EUR")) -> % | J54: =IFERROR(J52/J11, "-") -> 0.17473654 | K54: =IFERROR(K52/K11, "-") -> 0.098715479 | L54: =IFERROR(L52/L11, "-") -> 0.095354026 | M54: =IFERROR(M52/M11, "-") -> 0.071493331 | N54: =IFERROR(N52/N11, "-") -> 0.040320995
G55: =IF(M55="","",IF(AND(M55>=-1,M55<=1), "%","mln EUR"))
D56: thereof profit attributable to non-controlling interests | F56: Annual statement | G56: =IF(M56="","",IF(AND(M56>=-1,M56<=1), "%","mln EUR")) -> mln EUR | J56: 390 | K56: 308 | L56: 270 | M56: 202 | N56: 190
E57: Change YoY | F57: Calcs | G57: =IF(M57="","",IF(AND(M57>=-1,M57<=1), "%","mln EUR")) -> % | K57: =IFERROR(K56/J56-1, "-") -> -0.21025641 | L57: =IFERROR(L56/K56-1, "-") -> -0.12337662 | M57: =IFERROR(M56/L56-1, "-") -> -0.25185185 | N57: =IFERROR(N56/M56-1, "-") -> -0.059405941
G58: =IF(M58="","",IF(AND(M58>=-1,M58<=1), "%","mln EUR"))
D59: thereof profit attributable to shareholders of Mercedes-Benz Group AG | F59: Annual statement | G59: =IF(M59="","",IF(AND(M59>=-1,M59<=1), "%","mln EUR")) -> mln EUR | J59: 23006 | K59: 14501 | L59: 14261 | M59: 10207 | N59: 5141
E60: Change YoY | F60: Calcs | G60: =IF(M60="","",IF(AND(M60>=-1,M60<=1), "%","mln EUR")) -> % | K60: =IFERROR(K59/J59-1, "-") -> -0.36968617 | L60: =IFERROR(L59/K59-1, "-") -> -0.016550583 | M60: =IFERROR(M59/L59-1, "-") -> -0.28427179 | N60: =IFERROR(N59/M59-1, "-") -> -0.49632605
D63: Earnings per share
E65: Basic | F65: Annual statement | G65: =IF(M65="","",IF(AND(M65>=-1,M65<=1), "%","EUR")) -> EUR | M65: 10.19 | N65: 5.34
E67: Diluted | F67: Annual statement | G67: =IF(M67="","",IF(AND(M67>=-1,M67<=1), "%","EUR")) -> EUR | M67: 10.19 | N67: 5.34

Sheet CF
A5: Cashflow statement | F5: Source | G5: UoM | I5: Const | J5: 2021A | K5: 2022A | L5: 2023A | M5: 2024A | N5: 2025A
B7: Cash and cash equivalents
C9: Cash and cash equivalents at beginning of period
D11: Cash and cash equivalents ta beginning of period | F11: Annual statement | G11: =IF(M11="","",IF(AND(M11>=-1,M11<=1), "%","mln EUR")) -> mln EUR | J11: 23048 | K11: 23182 | L11: 17679 | M11: 15972 | N11: 14516
D12: less cash and cash equivalents classified as assets held for sale at beginning of year | F12: Annual statement | G12: =IF(M12="","",IF(AND(M12>=-1,M12<=1), "%","mln EUR")) -> mln EUR | J12: 0 | K12: 0 | L12: 0 | M12: 10 | N12: 5
G13: =IF(M13="","",IF(AND(M13>=-1,M13<=1), "%","mln EUR"))
D14: Cash and cash equivalents at beginning of year (Consolidated Statement of Financial Position) | F14: Annual statement | G14: =IF(M14="","",IF(AND(M14>=-1,M14<=1), "%","mln EUR")) -> mln EUR | J14: 23048 | K14: 23182 | L14: 17679 | M14: 15962 | N14: 14511
G15: =IF(M15="","",IF(AND(M15>=-1,M15<=1), "%","mln EUR"))
B16: Cashflow from operating activities
G17: =IF(M17="","",IF(AND(M17>=-1,M17<=1), "%","mln EUR"))
C18: Profit from continuing operations
G19: =IF(M19="","",IF(AND(M19>=-1,M19<=1), "%","mln EUR"))
D20: Profit from continuing operations | F20: Annual statement | G20: =IF(M20="","",IF(AND(M20>=-1,M20<=1), "%","mln EUR")) -> mln EUR | J20: 28775 | K20: 20304 | L20: 20084 | M20: 14147 | N20: 6284
D21: Depreciation and amortisation/impairments | F21: Annual statement | G21: =IF(M21="","",IF(AND(M21>=-1,M21<=1), "%","mln EUR")) -> mln EUR | J21: 6980 | K21: 6521 | L21: 6663 | M21: 6772 | N21: 7223
D22: Other non-cash expense and income | F22: Annual statement | G22: =IF(M22="","",IF(AND(M22>=-1,M22<=1), "%","mln EUR")) -> mln EUR | J22: -11503 | K22: -1296 | L22: -2369 | M22: -1362 | N22: -1204
D23: Gains (-)/losses (+) from disposals of non-current assets | F23: Annual statement | G23: =IF(M23="","",IF(AND(M23>=-1,M23<=1), "%","mln EUR")) -> mln EUR | J23: -695 | K23: -990 | L23: -92 | M23: 18 | N23: 65
G24: =IF(M24="","",IF(AND(M24>=-1,M24<=1), "%","mln EUR"))
C25: Change in operating assets and liabilities
G26: =IF(M26="","",IF(AND(M26>=-1,M26<=1), "%","mln EUR"))
D27: Inventories | F27: Annual statement | G27: =IF(M27="","",IF(AND(M27>=-1,M27<=1), "%","mln EUR")) -> mln EUR | J27: -2561 | K27: -4111 | L27: -2420 | M27: 737 | N27: 724
D28: Trade receivables and trade liabilities | F28: Annual statement | G28: =IF(M28="","",IF(AND(M28>=-1,M28<=1), "%","mln EUR")) -> mln EUR | J28: 1694 | K28: 1029 | L28: 1310 | M28: -1199 | N28: 895
D29: Receivables from financial services | F29: Annual statement | G29: =IF(M29="","",IF(AND(M29>=-1,M29<=1), "%","mln EUR")) -> mln EUR | J29: 3879 | K29: -5327 | L29: -6125 | M29: 3280 | N29: 5828
D30: Vehicles on operating leases | F30: Annual statement | G30: =IF(M30="","",IF(AND(M30>=-1,M30<=1), "%","mln EUR")) -> mln EUR | J30: 1428 | K30: 3810 | L30: -640 | M30: -3110 | N30: -4060
D31: Other operating assets and liabilities | F31: Annual statement | G31: =IF(M31="","",IF(AND(M31>=-1,M31<=1), "%","mln EUR")) -> mln EUR | J31: -1261 | K31: 358 | L31: 1624 | M31: 986 | N31: 2585
G32: =IF(M32="","",IF(AND(M32>=-1,M32<=1), "%","mln EUR"))
D33: Dividends received from equity-method investments | F33: Annual statement | G33: =IF(M33="","",IF(AND(M33>=-1,M33<=1), "%","mln EUR")) -> mln EUR | J33: 1625 | K33: 1605 | L33: 2056 | M33: 1918 | N33: 1330
D34: Income taxes paid | F34: Annual statement | G34: =IF(M34="","",IF(AND(M34>=-1,M34<=1), "%","mln EUR")) -> mln EUR | J34: -3812 | K34: -5009 | L34: -5621 | M34: -4452 | N34: -1664
G35: =IF(M35="","",IF(AND(M35>=-1,M35<=1), "%","mln EUR"))
C36: Total cashflow from operating activities
G37: =IF(M37="","",IF(AND(M37>=-1,M37<=1), "%","mln EUR"))
D38: Total cashflow from operating activities | F38: Annual statement | G38: =IF(M38="","",IF(AND(M38>=-1,M38<=1), "%","mln EUR")) -> mln EUR | J38: 24549 | K38: 16894 | L38: 14470 | M38: 17735 | N38: 18006
G39: =IF(M39="","",IF(AND(M39>=-1,M39<=1), "%","mln EUR"))
B40: Cashflow from investing activities
C42: Cashflow from investing activities
G43: =IF(M43="","",IF(AND(M43>=-1,M43<=1), "%","mln EUR"))
D44: Additions to property, plant and equipment | F44: Annual statement | G44: =IF(M44="","",IF(AND(M44>=-1,M44<=1), "%","mln EUR")) -> mln EUR | J44: -4579 | K44: -3481 | L44: -3745 | M44: -4039 | N44: -5482
D45: Additions to intangible assets | F45: Annual statement | G45: =IF(M45="","",IF(AND(M45>=-1,M45<=1), "%","mln EUR")) -> mln EUR | J45: -2741 | K45: -3418 | L45: -4468 | M45: -4626 | N45: -4260
D46: Investments in shareholdings | F46: Annual statement | G46: =IF(M46="","",IF(AND(M46>=-1,M46<=1), "%","mln EUR")) -> mln EUR | J46: -573 | K46: -849 | L46: -334 | M46: -363 | N46: -304
D47: Cash inflows from disposals of shareholdings and other business operations | F47: Annual statement | G47: =IF(M47="","",IF(AND(M47>=-1,M47<=1), "%","mln EUR")) -> mln EUR | J47: 793 | K47: 3337 | L47: 612 | M47: 716 | N47: 413
D48: Acquisition of marketable debt securities and similar investments | F48: Annual statement | G48: =IF(M48="","",IF(AND(M48>=-1,M48<=1), "%","mln EUR")) -> mln EUR | J48: -5694 | K48: -2622 | L48: -4714 | M48: -6785 | N48: -12303
D49: Cash inflows from sales of marketable debt securities and similar investments | F49: Annual statement | G49: =IF(M49="","",IF(AND(M49>=-1,M49<=1), "%","mln EUR")) -> mln EUR | J49: 4385 | K49: 3084 | L49: 5021 | M49: 6160 | N49: 12557
D50: Cash inflows from disposals of property, plant and equipment and intangible assets | F50: Annual statement | G50: =IF(M50="","",IF(AND(M50>=-1,M50<=1), "%","mln EUR")) -> mln EUR | J50: 826 | K50: 469 | L50: 285 | M50: 188 | N50: 191
D51: Other | F51: Annual statement | G51: =IF(M51="","",IF(AND(M51>=-1,M51<=1), "%","mln EUR")) -> % | J51: -7 | K51: 27 | L51: 28 | M51: -1 | N51: -12
G52: =IF(M52="","",IF(AND(M52>=-1,M52<=1), "%","mln EUR"))
C53: Total cashflow from investing activities
G54: =IF(M54="","",IF(AND(M54>=-1,M54<=1), "%","mln EUR"))
D55: Total cashflow from investing activities | F55: Annual statement | G55: =IF(M55="","",IF(AND(M55>=-1,M55<=1), "%","mln EUR")) -> mln EUR | J55: -6226 | K55: -3453 | L55: -7315 | M55: -8750 | N55: -9200
G56: =IF(M56="","",IF(AND(M56>=-1,M56<=1), "%","mln EUR"))
B57: Cashflow from financing activities
C59: Cashflow from financingactivities
G60: =IF(M60="","",IF(AND(M60>=-1,M60<=1), "%","mln EUR"))
D61: Change in short-term financing liabilities | F61: Annual statement | G61: =IF(M61="","",IF(AND(M61>=-1,M61<=1), "%","mln EUR")) -> mln EUR | J61: 1463 | K61: 172 | L61: -512 | M61: -3171 | N61: -3558
D62: Additions to long-term financing liabilities | F62: Annual statement | G62: =IF(M62="","",IF(AND(M62>=-1,M62<=1), "%","mln EUR")) -> mln EUR | J62: 42196 | K62: 38429 | L62: 39288 | M62: 38338 | N62: 28598
D63: Repayment of long-term financing liabilities | F63: Annual statement | G63: =IF(M63="","",IF(AND(M63>=-1,M63<=1), "%","mln EUR")) -> mln EUR | J63: -60859 | K63: -51945 | L63: -39473 | M63: -35355 | N63: -30970
D64: Dividend paid to shareholders of Mercedes-Benz Group AG | F64: Annual statement | G64: =IF(M64="","",IF(AND(M64>=-1,M64<=1), "%","mln EUR")) -> mln EUR | J64: -1444 | K64: -5349 | L64: -5556 | M64: -5486 | N64: -4140
D65: Dividends paid to non-controlling interests | F65: Annual statement | G65: =IF(M65="","",IF(AND(M65>=-1,M65<=1), "%","mln EUR")) -> mln EUR | J65: -366 | K65: -320 | L65: -324 | M65: -239 | N65: -183
D66: Acquisition of treasury shares | F66: Annual statement | G66: =IF(M66="","",IF(AND(M66>=-1,M66<=1), "%","mln EUR")) -> mln EUR | J66: 0 | K66: 0 | L66: -1941 | M66: -4921 | N66: -360
D67: Other cash inflows | F67: Annual statement | G67: =IF(M67="","",IF(AND(M67>=-1,M67<=1), "%","mln EUR")) -> mln EUR | J67: -49 | K67: -19 | L67: 127 | M67: 82 | N67: 160
G68: =IF(M68="","",IF(AND(M68>=-1,M68<=1), "%","mln EUR"))
C69: Total cashflow from financing activities
G70: =IF(M70="","",IF(AND(M70>=-1,M70<=1), "%","mln EUR"))
D71: Total cashflow from financing activities | F71: Annual statement | G71: =IF(M71="","",IF(AND(M71>=-1,M71<=1), "%","mln EUR")) -> mln EUR | J71: -19059 | K71: -19032 | L71: -8391 | M71: -10752 | N71: -10453
G72: =IF(M72="","",IF(AND(M72>=-1,M72<=1), "%","mln EUR"))
B73: Changes in cash and cash equivalents
G74: =IF(M74="","",IF(AND(M74>=-1,M74<=1), "%","mln EUR"))
C75: Cash and cash equivalents the the end of the period
G76: =IF(M76="","",IF(AND(M76>=-1,M76<=1), "%","mln EUR"))
D77: Cash and cash equivalents the the end of the period | F77: Annual statement | G77: =IF(M77="","",IF(AND(M77>=-1,M77<=1), "%","mln EUR")) -> mln EUR | J77: 23182 | K77: 17679 | L77: 15972 | M77: 14516 | N77: 12276
D78: thereof cash and cash equivalents classified as assets held for sale at end of period | F78: Annual statement | G78: =IF(M78="","",IF(AND(M78>=-1,M78<=1), "%","mln EUR")) -> mln EUR | J78: 62 | K78: 0 | L78: 10 | M78: 5 | N78: 22
G79: =IF(M79="","",IF(AND(M79>=-1,M79<=1), "%","mln EUR"))
D80: Cash and cash equivalents at end of year (Consolidated Statement of Financial Position) | F80: Annual statement | G80: =IF(M80="","",IF(AND(M80>=-1,M80<=1), "%","mln EUR")) -> mln EUR | J80: 23120 | K80: 17679 | L80: 15962 | M80: 14511 | N80: 12254
G81: =IF(M81="","",IF(AND(M81>=-1,M81<=1), "%","mln EUR"))
C82: Net change in cash and cash eqivalents | G82: =IF(M82="","",IF(AND(M82>=-1,M82<=1), "%","mln EUR"))
G83: =IF(M83="","",IF(AND(M83>=-1,M83<=1), "%","mln EUR"))
D84: Net change in cash and cash eqivalents | F84: Calcs | G84: =IF(M84="","",IF(AND(M84>=-1,M84<=1), "%","mln EUR")) -> mln EUR | J84: =J77-J11 -> 134 | K84: =K77-K11 -> -5503 | L84: =L77-L11 -> -1707 | M84: =M77-M11 -> -1456 | N84: =N77-N11 -> -2240

Sheet 2. Calcs

Sheet EBITDA
A5: EBITDA | F5: Source | G5: UoM | I5: Const | J5: 2021A | K5: 2022A | L5: 2023A | M5: 2024A | N5: 2025A
D8: EBIT (from the IS) | F8: Link | G8: =IF(M8="","",IF(AND(M8>=-1,M8<=1), "%","mln EUR")) -> mln EUR | J8: =PL!J39 -> 16028 | K8: =PL!K39 -> 20458 | L8: =PL!L39 -> 19660 | M8: =PL!M39 -> 13599 | N8: =PL!N39 -> 5820
D9: + Depreciation & Amortization | F9: AS Note 34 | G9: =IF(M9="","",IF(AND(M9>=-1,M9<=1), "%","mln EUR")) -> mln EUR | J9: 15066 | K9: 13891 | L9: 13697 | M9: 14680 | N9: =15121 -> 15121
G10: =IF(M10="","",IF(AND(M10>=-1,M10<=1), "%","mln EUR"))
D11: Non-operating items | G11: =IF(M11="","",IF(AND(M11>=-1,M11<=1), "%","mln EUR"))
G12: =IF(M12="","",IF(AND(M12>=-1,M12<=1), "%","mln EUR"))
D13: (-)Other operating income | F13: AS Note 6 | G13: =IF(M13="","",IF(AND(M13>=-1,M13<=1), "%","mln EUR")) -> mln EUR | J13: -2888 | K13: -3323 | L13: -2206 | M13: -2507 | N13: =-1551 -> -1551
D14: (+)Other operating expense | F14: AS Note 6 | G14: =IF(M14="","",IF(AND(M14>=-1,M14<=1), "%","mln EUR")) -> mln EUR | J14: 1735 | K14: 1289 | L14: 516 | M14: 483 | N14: =1025 -> 1025
D15: (-)Other financial income/expenses | F15: AS Note 7 | G15: =IF(M15="","",IF(AND(M15>=-1,M15<=1), "%","mln EUR")) -> mln EUR | J15: -317 | K15: -340 | L15: -108 | M15: 37 | N15: =-93 -> -93
D16: (-)Gains and losses on equity-method investments | F16: AS Note 13 | G16: =IF(M16="","",IF(AND(M16>=-1,M16<=1), "%","mln EUR")) -> mln EUR | J16: -1352 | K16: -1732 | L16: -2129 | M16: -1138 | N16: =-1118 -> -1118
D18: EBITDA | F18: Calcs | J18: =J8+J9+J13+J14+J15+J16 -> 28272 | K18: =K8+K9+K13+K14+K15+K16 -> 30243 | L18: =L8+L9+L13+L14+L15+L16 -> 29430 | M18: =M8+M9+M13+M14+M15+M16 -> 25154 | N18: =N8+N9+N13+N14+N15+N16 -> 19204
C20: Net Profit
D22: Net Profit | F22: Link | G22: =IF(M22="","",IF(AND(M22>=-1,M22<=1), "%","mln EUR")) -> mln EUR | J22: =PL!J52 -> 23396 | K22: =PL!K52 -> 14809 | L22: =PL!L52 -> 14531 | M22: =PL!M52 -> 10409 | N22: =PL!N52 -> 5331
D23: Revenue | F23: Link | G23: =IF(M23="","",IF(AND(M23>=-1,M23<=1), "%","mln EUR")) -> mln EUR | J23: =PL!J11 -> 133893 | K23: =PL!K11 -> 150017 | L23: =PL!L11 -> 152390 | M23: =PL!M11 -> 145594 | N23: =PL!N11 -> 132214
C25: Margins
D27: EBITDA margin | F27: Calcs | G27: =IF(M27="","",IF(AND(M27>=-1,M27<=1), "%","mln EUR")) -> % | J27: =J18/J23 -> 0.21115368 | K27: =K18/K23 -> 0.20159715 | L27: =L18/L23 -> 0.19312291 | M27: =M18/M23 -> 0.17276811 | N27: =N18/N23 -> 0.14524937
D28: EBIT margin | F28: Link | G28: =IF(M28="","",IF(AND(M28>=-1,M28<=1), "%","mln EUR")) -> % | J28: =J8/J23 -> 0.11970753 | K28: =K8/K23 -> 0.13637121 | L28: =L8/L23 -> 0.12901109 | M28: =M8/M23 -> 0.093403574 | N28: =N8/N23 -> 0.044019544

Sheet Ratios
C1: Variable | D1: Value | E1: Source
C3: Current share price as of 29 May 2026 in EUR | D3: 52.19 | E3: https://finance.yahoo.com/quote/MBG.DE
C4: Number of shares issued as of 30 September 2025 in mln EUR | D4: =962903703/1000000 -> 962.9037 | E4: https://group.mercedes-benz.com/investors/share/
C5: Cash and cash equivalents | D5: =BS!N57 -> 12254 | E5: Annual statement
C6: Total Debt (LT Debt + ST Debt + Lease) in mln EUR | D6: =BS!N95+BS!N129+888 -> 100894 | E6: AS Note 24
C7: Net Debt (Total Debt - Cash & Cash Equivalents in mln EUR | D7: =D6-BS!N57 -> 88640 | E7: Annual statement

Sheet 3. Comps

Sheet BMW
A1: Link: https://www.bmwgroup.com/content/dam/grpw/websites/bmwgroup_com/ir/downloads/en/2026/bericht/BMW-Group-Report-2025-en.pdf
E3: Source | F3: UoM | H3: Const | I3: 2025A
B4: Income statement (P&L) | F4: Source | G4: UoM | I4: 2025A
B5: PAGE 271
D6: Revenue | F6: Annual statement | G6: mln EUR | I6: 133453
G7: =IF(I7="","",IF(AND(I7>=-1,I7<=1), "%","mln EUR"))
D8: Cost of goods sold | F8: Annual statement | G8: =IF(I8="","",IF(AND(I8>=-1,I8<=1), "%","mln EUR")) -> mln EUR | I8: =-112858 -> -112858
G9: =IF(I9="","",IF(AND(I9>=-1,I9<=1), "%","mln EUR"))
D10: Gross profit | F10: Annual statement | G10: =IF(I10="","",IF(AND(I10>=-1,I10<=1), "%","mln EUR")) -> mln EUR | I10: =I8+I6 -> 20595
G11: =IF(I11="","",IF(AND(I11>=-1,I11<=1), "%","mln EUR"))
D12: SGA | F12: Annual statement | G12: =IF(I12="","",IF(AND(I12>=-1,I12<=1), "%","mln EUR")) -> mln EUR | I12: =-10606 -> -10606
G13: =IF(I13="","",IF(AND(I13>=-1,I13<=1), "%","mln EUR"))
D14: Other operating income/expense | F14: Annual statement | G14: mln EUR | I14: =1556-1359 -> 197
G15: =IF(I15="","",IF(AND(I15>=-1,I15<=1), "%","mln EUR"))
D16: Gains/losses on equity-method invesments, net | F16: Annual statement | G16: =IF(I16="","",IF(AND(I16>=-1,I16<=1), "%","mln EUR")) -> mln EUR | I16: 38
G17: =IF(I17="","",IF(AND(I17>=-1,I17<=1), "%","mln EUR"))
D18: Other financial income/expense, net | F18: Annual statement | G18: =IF(I18="","",IF(AND(I18>=-1,I18<=1), "%","mln EUR")) -> mln EUR | I18: 72
G19: =IF(I19="","",IF(AND(I19>=-1,I19<=1), "%","mln EUR"))
D20: EBIT | F20: Annual statement | G20: =IF(I20="","",IF(AND(I20>=-1,I20<=1), "%","mln EUR")) -> mln EUR | I20: =I10+I12+I14+I16+I18 -> 10296
G21: =IF(I21="","",IF(AND(I21>=-1,I21<=1), "%","mln EUR"))
D22: Interest income | F22: Annual statement | G22: =IF(I22="","",IF(AND(I22>=-1,I22<=1), "%","mln EUR")) -> mln EUR | I22: =502-562 -> -60
G23: =IF(I23="","",IF(AND(I23>=-1,I23<=1), "%","mln EUR"))
D24: Profit before income taxes | F24: Annual statement | G24: =IF(I24="","",IF(AND(I24>=-1,I24<=1), "%","mln EUR")) -> mln EUR | I24: =10236 -> 10236
G25: =IF(I25="","",IF(AND(I25>=-1,I25<=1), "%","mln EUR"))
D26: Income taxes | F26: Annual statement | G26: =IF(I26="","",IF(AND(I26>=-1,I26<=1), "%","mln EUR")) -> mln EUR | I26: =-2785 -> -2785
G27: =IF(I27="","",IF(AND(I27>=-1,I27<=1), "%","mln EUR"))
D28: Net profit | F28: Annual statement | G28: =IF(I28="","",IF(AND(I28>=-1,I28<=1), "%","mln EUR")) -> mln EUR | I28: =7451 -> 7451
C31: EBITDA
D33: EBIT (from the IS) | F33: Link | G33: =IF(M33="","",IF(AND(M33>=-1,M33<=1), "%","mln EUR")) | I33: =I20 -> 10296
D34: + Depreciation & Amortization | F34: AS Note 46, page 349 | G34: =IF(M34="","",IF(AND(M34>=-1,M34<=1), "%","mln EUR")) | I34: 15219
G35: =IF(M35="","",IF(AND(M35>=-1,M35<=1), "%","mln EUR"))
D36: Non-operating items | G36: =IF(M36="","",IF(AND(M36>=-1,M36<=1), "%","mln EUR"))
G37: =IF(M37="","",IF(AND(M37>=-1,M37<=1), "%","mln EUR"))
D38: (-)Other operating income | F38: Page 271 | G38: =IF(M38="","",IF(AND(M38>=-1,M38<=1), "%","mln EUR")) | I38: -1556
D39: (+)Other operating expense | F39: Page 271 | G39: =IF(M39="","",IF(AND(M39>=-1,M39<=1), "%","mln EUR")) | I39: 1359
D40: (-)Other financial income/expenses | F40: AS Note 7 | G40: =IF(M40="","",IF(AND(M40>=-1,M40<=1), "%","mln EUR")) | I40: =-I18 -> -72
D41: (-)Gains and losses on equity-method investments | F41: AS Note 13 | G41: =IF(M41="","",IF(AND(M41>=-1,M41<=1), "%","mln EUR")) | I41: =-I16 -> -38
D43: EBITDA | F43: Calcs | I43: =I33+I34+I38+I39+I40+I41 -> 25208
C45: Net Profit
D47: Net Profit | F47: Link | G47: =IF(M47="","",IF(AND(M47>=-1,M47<=1), "%","mln EUR")) | I47: =I28 -> 7451
D48: Revenue | F48: Link | G48: =IF(M48="","",IF(AND(M48>=-1,M48<=1), "%","mln EUR")) | I48: =I6 -> 133453
C50: Margins
D52: EBITDA margin | F52: Calcs | G52: =IF(M52="","",IF(AND(M52>=-1,M52<=1), "%","mln EUR")) | I52: =I43/I48 -> 0.18889047
D53: EBIT margin | F53: Link | G53: =IF(M53="","",IF(AND(M53>=-1,M53<=1), "%","mln EUR")) | I53: =I33/I48 -> 0.077150757
B56: Balance Sheet (BS) | F56: Source | G56: UoM | I56: 2025A
D58: Total equity and liabilities | F58: Annual statement | G58: mln EUR | I58: 265967
D60: Cash & Cash equivalents | F60: Annual statement | G60: mln EUR | I60: 18854
C62: Equity | F62: Source | G62: UoM | I62: 2025A
C64: Equity attributable to shareholders of BMW AG
D66: Share capital | F66: Annual statement | G66: mln EUR | I66: =616 -> 616
D69: Capital reserves | F69: Annual statement | G69: mln EUR | I69: 2479
D72: Retained earnings | F72: Annual statement | G72: mln EUR | I72: 95471
D75: Other reserves | F75: Annual statement | G75: mln EUR | I75: =-2168 -> -2168
D78: Treasury shares | F78: Annual statement | G78: mln EUR | I78: =-701 -> -701
C81: Total equity to shareholders
D83: Total equity to shareholders | F83: Annual statement | G83: mln EUR | I83: =SUM(I66:I79) -> 95697
C86: Non-controlling interest
D88: Non-controlling interest | F88: Annual statement | G88: mln EUR | I88: =2209 -> 2209
C91: Total Debt & Equity
D93: Total equity | F93: Annual statement | G93: mln EUR | I93: =I83+I88 -> 97906
D95: Total Debt | F95: Annual statement | G95: mln EUR | I95: =I58-I93 -> 168061
D96: Of these, financial liabilities | F96: Annual statement | G96: mln EUR | I96: 110469
B98: Stock | F98: Source | G98: UoM
D100: Price (31.12.2025) | F100: https://ru.investing.com/equities/bay-mot-werke | G100: EUR | I100: =93.24 -> 93.24
D102: Price (21.05.2026) | F102: https://ru.investing.com/equities/bay-mot-werke | G102: EUR | I102: =74.11 -> 74.11
D104: Price of a preffered share (21.05.2026) | F104: https://www.investing.com/equities/bmw-ag-vz | G104: EUR | I104: 74.35
D106: Average number of ordinary shares in circulation number | F106: Annual statement, page 296 | G106: Number | I106: 559313364
D108: Average number of preferred shares in circulation | F108: Annual statement, page 296 | G108: Number | I108: 54225635
D110: Dividend per ordinary share | F110: Annual statement, page 296 | G110: EUR | I110: 4.4
D112: Dividend per preferred share | F112: Annual statement, page 296 | G112: EUR | I112: 4.42
D114: Market equity value | F114: Calcs | G114: EUR | I114: =I106*I102 -> 4.1450713e+10
D116: EV - Enterprise Value | F116: Calcs | G116: EUR | I116: =I114+(I96-I60+I88)*1000000+I108*I104 -> 1.3930639e+11
B118: Multiples | F118: Source | G118: UoM
D120: P/E (21.05.2026) | F120: Calcs | G120: Number | I120: =I102/I124 -> 6.2329689
D122: P/E (31.12.2025) | F122: Calcs | G122: Number | I122: =I100/I124 -> 7.8418839
D124: Basic earnings per ordinary share | F124: Annual statement, page 69 | G124: =IF(I124="","",IF(AND(I124>=-1,I124<=1),"%","EUR")) -> EUR | I124: =11.89 -> 11.89
D126: Basic earnings per preferred share | F126: Annual statement, page 69 | G126: =IF(I126="","",IF(AND(I126>=-1,I126<=1),"%","EUR")) -> EUR | I126: =11.91 -> 11.91
D128: EV/EBITDA | F128: Calcs | G128: Number | I128: =I116/(I43*1000000) -> 5.526277

Sheet VW
A1: Link: https://uploads.vw-mms.de/system/production/documents/cws/003/212/file_en/41966a4270c8a0a4185b3ab69eaa433cf6892168/annual-report-2025-volkswagen-group.pdf?1773224256
A2: https://finance.yahoo.com/quote/VOW3.DE/history/
E3: Source | F3: UoM | H3: Const | I3: 2025A
B4: Income statement (P&L) | F4: Source | G4: UoM | I4: 2025A
D6: Revenue | F6: Annual statement | G6: mln EUR | I6: 321913
G7: =IF(I7="","",IF(AND(I7>=-1,I7<=1), "%","mln EUR"))
D8: Cost of goods sold | F8: Annual statement | G8: =IF(I8="","",IF(AND(I8>=-1,I8<=1), "%","mln EUR")) -> mln EUR | I8: -270671
G9: =IF(I9="","",IF(AND(I9>=-1,I9<=1), "%","mln EUR"))
D10: Gross profit | F10: Annual statement | G10: =IF(I10="","",IF(AND(I10>=-1,I10<=1), "%","mln EUR")) -> mln EUR | I10: =I6+I8 -> 51242
G11: =IF(I11="","",IF(AND(I11>=-1,I11<=1), "%","mln EUR"))
D12: SGA | F12: Annual statement | G12: =IF(I12="","",IF(AND(I12>=-1,I12<=1), "%","mln EUR")) -> mln EUR | I12: =-22804-12541 -> -35345
G13: =IF(I13="","",IF(AND(I13>=-1,I13<=1), "%","mln EUR"))
D14: Other operating income/expense | F14: Annual statement | G14: mln EUR | I14: =-7029 -> -7029
G15: =IF(I15="","",IF(AND(I15>=-1,I15<=1), "%","mln EUR"))
D16: Gains/losses on equity-method invesments, net | F16: Annual statement, Note 7, page 503 | G16: =IF(I16="","",IF(AND(I16>=-1,I16<=1), "%","mln EUR")) -> mln EUR | I16: 930
G17: =IF(I17="","",IF(AND(I17>=-1,I17<=1), "%","mln EUR"))
D18: Other financial income/expense, net | F18: Annual statement, Note 9, page 504 | G18: =IF(I18="","",IF(AND(I18>=-1,I18<=1), "%","mln EUR")) -> mln EUR | I18: 930
G19: =IF(I19="","",IF(AND(I19>=-1,I19<=1), "%","mln EUR"))
D20: EBIT | F20: Annual statement | G20: =IF(I20="","",IF(AND(I20>=-1,I20<=1), "%","mln EUR")) -> mln EUR | I20: =I10+I12+I14+I16+I18 -> 10728
G21: =IF(I21="","",IF(AND(I21>=-1,I21<=1), "%","mln EUR"))
D22: Interest income | F22: Annual statement, Note 8, page 504 | G22: =IF(I22="","",IF(AND(I22>=-1,I22<=1), "%","mln EUR")) -> mln EUR | I22: 1824
G23: =IF(I23="","",IF(AND(I23>=-1,I23<=1), "%","mln EUR"))
D24: Profit before income taxes | F24: Annual statement | G24: =IF(I24="","",IF(AND(I24>=-1,I24<=1), "%","mln EUR")) -> mln EUR | I24: =I20+I22 -> 12552
G25: =IF(I25="","",IF(AND(I25>=-1,I25<=1), "%","mln EUR"))
D26: Income taxes | F26: Annual statement | G26: =IF(I26="","",IF(AND(I26>=-1,I26<=1), "%","mln EUR")) -> mln EUR | I26: -2403
G27: =IF(I27="","",IF(AND(I27>=-1,I27<=1), "%","mln EUR"))
D28: Net profit | F28: Annual statement | G28: =IF(I28="","",IF(AND(I28>=-1,I28<=1), "%","mln EUR")) -> mln EUR | I28: =I24+I26 -> 10149
C31: EBITDA
D33: EBIT (from the IS) | F33: Link | G33: =IF(M33="","",IF(AND(M33>=-1,M33<=1), "%","mln EUR")) | I33: =I20 -> 10728
D34: + Depreciation & Amortization | F34: Annual statement, CF | G34: =IF(M34="","",IF(AND(M34>=-1,M34<=1), "%","mln EUR")) | I34: =16866+8365 -> 25231
G35: =IF(M35="","",IF(AND(M35>=-1,M35<=1), "%","mln EUR"))
D36: Non-operating items | G36: =IF(M36="","",IF(AND(M36>=-1,M36<=1), "%","mln EUR"))
G37: =IF(M37="","",IF(AND(M37>=-1,M37<=1), "%","mln EUR"))
D38: (-)Other operating income | F38: Annual statement | G38: =IF(M38="","",IF(AND(M38>=-1,M38<=1), "%","mln EUR"))
D39: (+)Other operating expense | F39: Annual statement | G39: =IF(M39="","",IF(AND(M39>=-1,M39<=1), "%","mln EUR")) | I39: =-I14 -> 7029
D40: (-)Other financial income/expenses | F40: Annual statement | G40: =IF(M40="","",IF(AND(M40>=-1,M40<=1), "%","mln EUR")) | I40: =-I18 -> -930
D41: (-)Gains and losses on equity-method investments | F41: Annual statement | G41: =IF(M41="","",IF(AND(M41>=-1,M41<=1), "%","mln EUR")) | I41: =-I16 -> -930
D43: EBITDA | F43: Calcs | I43: =I33+I34+I38+I39+I40+I41 -> 41128
C45: Net Profit
D47: Net Profit | F47: Link | G47: =IF(M47="","",IF(AND(M47>=-1,M47<=1), "%","mln EUR")) | I47: =I28 -> 10149
D48: Revenue | F48: Link | G48: =IF(M48="","",IF(AND(M48>=-1,M48<=1), "%","mln EUR")) | I48: =I6 -> 321913
C50: Margins
D52: EBITDA margin | F52: Calcs | G52: =IF(M52="","",IF(AND(M52>=-1,M52<=1), "%","mln EUR")) | I52: =I43/I48 -> 0.12776123
D53: EBIT margin | F53: Link | G53: =IF(M53="","",IF(AND(M53>=-1,M53<=1), "%","mln EUR")) | I53: =I33/I48 -> 0.033325774
B56: Balance Sheet (BS) | F56: Source | G56: UoM | I56: 2025A
D58: Total equity and liabilities | F58: Annual statement | G58: mln EUR | I58: 644467
D60: Cash & Cash equivalents | F60: Annual statement | G60: mln EUR | I60: 38801
C62: Equity | F62: Source | G62: UoM | I62: 2025A
C64: Equity attributable to shareholders of AUDI
D66: Share capital | F66: Annual statement, BS | G66: mln EUR | I66: 1283
D69: Capital reserves | F69: Annual statement, BS | G69: mln EUR | I69: 14551
D72: Retained earnings | F72: Annual statement, BS | G72: mln EUR | I72: 161357
D75: Other reserves | F75: Annual statement, BS | G75: mln EUR | I75: -3190
D78: Treasury shares | F78: Annual statement, BS | G78: mln EUR | I78: -
C81: Total equity to shareholders
D83: Total equity to shareholders | F83: Annual statement | G83: mln EUR | I83: =SUM(I66:I79) -> 174001
C86: Non-controlling interest
D88: Non-controlling interest | F88: Annual statement | G88: mln EUR | I88: 14777
C91: Total Debt & Equity
D93: Total equity | F93: Annual statement | G93: mln EUR | I93: =I83+I88 -> 188778
D95: Total Liabilities | F95: Annual statement | G95: mln EUR | I95: =I58-I93 -> 455689
D96: Of these, financial liabilities | F96: Annual statement | G96: mln EUR | I96: =127489+137214 -> 264703
B98: Stock | F98: Source | G98: UoM
D100: Price (31.12.2025) | F100: =A2 -> https://finance.yahoo.com/quote/VOW3.DE/history/ | G100: EUR | I100: 103
D102: Price (21.05.2026) | F102: =F100 -> https://finance.yahoo.com/quote/VOW3.DE/history/ | G102: EUR | I102: 88.5
D104: Average number of ordinary shares in circulation | F104: AS, Note 11, page 509 | G104: Number | I104: 295089818
D106: Average number of preferred shares in circulation | F106: AS, Note 11, page 509 | G106: Number | I106: 206205445
D108: Dividend per ordinary share | F108: AS, Note 24, page 522 | G108: EUR | I108: =5.2 -> 5.2
D110: Dividend per preferred share | F110: Annual statement | G110: EUR | I110: 5.26
D112: Market equity value | F112: Calcs | G112: EUR | I112: =(I104+I106)*I102 -> 4.4364631e+10
D114: EV - Enterprise Value | F114: Calcs | G114: EUR | I114: =I112+(I96-I60+I88)*1000000 -> 2.8504363e+11
B116: Multiples | F116: Source | G116: UoM
D118: P/E (21.05.2026) | F118: Calcs | G118: Number | I118: =I102/I124 -> 6.6292135
D120: P/E (31.12.2025) | F120: Calcs | G120: Number | I120: =I100/I124 -> 7.7153558
D122: Basic earnings per ordinary share | F122: AS Note 11, page 509 | G122: EUR | I122: 13.29
D124: Basic earnings per preferred share | F124: AS Note 11, page 509 | G124: EUR | I124: 13.35
D126: EV/EBITDA | F126: Calcs | G126: Number | I126: =I114/(I43*1000000) -> 6.9306465

Sheet Porsche
A1: Link: https://newsroom.porsche.com/en/annual-sustainability-report/consolidated-financial-statements/consolidated-income-statement/
A2: https://newsroom.porsche.com/assets/uploads/documents/Notes_to_the_consolidated_financial_statements_2025_Porsche_AG.pdf
E3: Source | F3: UoM | H3: Const | I3: 2025A
B4: Income statement (P&L) | F4: Source | G4: UoM | I4: 2025A
D6: Revenue | F6: Annual statement | G6: mln EUR | I6: 36272
G7: =IF(I7="","",IF(AND(I7>=-1,I7<=1), "%","mln EUR"))
D8: Cost of goods sold | F8: Annual statement | G8: =IF(I8="","",IF(AND(I8>=-1,I8<=1), "%","mln EUR")) -> mln EUR | I8: -31221
G9: =IF(I9="","",IF(AND(I9>=-1,I9<=1), "%","mln EUR"))
D10: Gross profit | F10: Annual statement | G10: =IF(I10="","",IF(AND(I10>=-1,I10<=1), "%","mln EUR")) -> mln EUR | I10: =I6+I8 -> 5051
G11: =IF(I11="","",IF(AND(I11>=-1,I11<=1), "%","mln EUR"))
D12: SGA | F12: Annual statement | G12: =IF(I12="","",IF(AND(I12>=-1,I12<=1), "%","mln EUR")) -> mln EUR | I12: -4694
G13: =IF(I13="","",IF(AND(I13>=-1,I13<=1), "%","mln EUR"))
D14: Other operating income/expense | F14: Annual statement | G14: mln EUR | I14: =1460-1403 -> 57
G15: =IF(I15="","",IF(AND(I15>=-1,I15<=1), "%","mln EUR"))
D16: Gains/losses on equity-method invesments, net | F16: Annual statement | G16: =IF(I16="","",IF(AND(I16>=-1,I16<=1), "%","mln EUR")) -> mln EUR | I16: -35
G17: =IF(I17="","",IF(AND(I17>=-1,I17<=1), "%","mln EUR"))
D18: Other financial income/expense, net | F18: Annual statement | G18: =IF(I18="","",IF(AND(I18>=-1,I18<=1), "%","mln EUR")) -> mln EUR | I18: =47 -> 47
G19: =IF(I19="","",IF(AND(I19>=-1,I19<=1), "%","mln EUR"))
D20: EBIT | F20: Annual statement | G20: =IF(I20="","",IF(AND(I20>=-1,I20<=1), "%","mln EUR")) -> mln EUR | I20: =I10+I12+I14+I16+I18 -> 426
G21: =IF(I21="","",IF(AND(I21>=-1,I21<=1), "%","mln EUR"))
D22: Interest income | F22: Annual statement | G22: =IF(I22="","",IF(AND(I22>=-1,I22<=1), "%","mln EUR")) -> mln EUR | I22: =188-169 -> 19
G23: =IF(I23="","",IF(AND(I23>=-1,I23<=1), "%","mln EUR"))
D24: Profit before income taxes | F24: Annual statement | G24: =IF(I24="","",IF(AND(I24>=-1,I24<=1), "%","mln EUR")) -> mln EUR | I24: =I20+I22 -> 445
G25: =IF(I25="","",IF(AND(I25>=-1,I25<=1), "%","mln EUR"))
D26: Income taxes | F26: Annual statement | G26: =IF(I26="","",IF(AND(I26>=-1,I26<=1), "%","mln EUR")) -> mln EUR | I26: -135
G27: =IF(I27="","",IF(AND(I27>=-1,I27<=1), "%","mln EUR"))
D28: Net profit | F28: Annual statement | G28: =IF(I28="","",IF(AND(I28>=-1,I28<=1), "%","mln EUR")) -> mln EUR | I28: =I24+I26 -> 310
C31: EBITDA
D33: EBIT (from the IS) | F33: Link | G33: =IF(M33="","",IF(AND(M33>=-1,M33<=1), "%","mln EUR")) | I33: =I20 -> 426
D34: + Depreciation & Amortization | F34: AS Note, page 351 (25) | G34: =IF(M34="","",IF(AND(M34>=-1,M34<=1), "%","mln EUR")) | I34: 3984
G35: =IF(M35="","",IF(AND(M35>=-1,M35<=1), "%","mln EUR"))
D36: Non-operating items | G36: =IF(M36="","",IF(AND(M36>=-1,M36<=1), "%","mln EUR"))
G37: =IF(M37="","",IF(AND(M37>=-1,M37<=1), "%","mln EUR"))
D38: (-)Other operating income | F38: Annual statement | G38: =IF(M38="","",IF(AND(M38>=-1,M38<=1), "%","mln EUR")) | I38: -1460
D39: (+)Other operating expense | F39: Annual statement | G39: =IF(M39="","",IF(AND(M39>=-1,M39<=1), "%","mln EUR")) | I39: 1403
D40: (-)Other financial income/expenses | F40: Annual statement | G40: =IF(M40="","",IF(AND(M40>=-1,M40<=1), "%","mln EUR")) | I40: =-I18 -> -47
D41: (-)Gains and losses on equity-method investments | F41: Annual statement | G41: =IF(M41="","",IF(AND(M41>=-1,M41<=1), "%","mln EUR")) | I41: =-I16 -> 35
D43: EBITDA | F43: Calcs | I43: =I33+I34+I38+I39+I40+I41 -> 4341
C45: Net Profit
D47: Net Profit | F47: Link | G47: =IF(M47="","",IF(AND(M47>=-1,M47<=1), "%","mln EUR")) | I47: =I28 -> 310
D48: Revenue | F48: Link | G48: =IF(M48="","",IF(AND(M48>=-1,M48<=1), "%","mln EUR")) | I48: =I6 -> 36272
C50: Margins
D52: EBITDA margin | F52: Calcs | G52: =IF(M52="","",IF(AND(M52>=-1,M52<=1), "%","mln EUR")) | I52: =I43/I48 -> 0.11967909
D53: EBIT margin | F53: Link | G53: =IF(M53="","",IF(AND(M53>=-1,M53<=1), "%","mln EUR")) | I53: =I33/I48 -> 0.011744596
B56: Balance Sheet (BS) | F56: Source | G56: UoM | I56: 2025A
D58: Total equity and liabilities | F58: Annual statement | G58: mln EUR | I58: 52715
D60: Cash & Cash equivalents | F60: Annual statement | G60: mln EUR | I60: 4996
C62: Equity | F62: Source | G62: UoM | I62: 2025A
C64: Equity attributable to shareholders of Porsche AG
D66: Share capital | F66: Annual statement | G66: mln EUR | I66: 911
D69: Capital reserves | F69: Annual statement | G69: mln EUR | I69: 3822
D72: Retained earnings | F72: Annual statement | G72: mln EUR | I72: 16886
D75: Other reserves | F75: Annual statement | G75: mln EUR | I75: 1372
D78: Treasury shares | F78: Annual statement | G78: mln EUR | I78: -
C81: Total equity to shareholders
D83: Total equity to shareholders | F83: Annual statement | G83: mln EUR | I83: =SUM(I66:I79) -> 22991
C86: Non-controlling interest
D88: Non-controlling interest | F88: Annual statement | G88: mln EUR | I88: 130
C91: Total Debt & Equity
D93: Total equity | F93: Annual statement | G93: mln EUR | I93: =I83+I88 -> 23121
D95: Total Liabilities | F95: Annual statement | G95: mln EUR | I95: =I58-I93 -> 29594
D96: Of these, financial liabilities | F96: AS Note 28, page 381 (55) | G96: mln EUR | I96: 11431
B98: Stock | F98: Source | G98: UoM
D100: Price (31.12.2025) | F100: https://ru.investing.com/equities/dr-ing-hc-f-porsche-prf | G100: EUR | I100: 45.62
D102: Price (21.05.2026) | F102: https://ru.investing.com/equities/dr-ing-hc-f-porsche-prf | G102: EUR | I102: 45.35
D104: Average number of ordinary shares in circulation | F104: AS Note 12, page 360 (34) | G104: Number | I104: 455500000
D106: Average number of preferred shares in circulation | F106: AS Note 12, page 360 (34) | G106: Number | I106: 455500000
D108: Dividend per ordinary share | F108: Annual statement | G108: EUR | I108: =(2101000000-4555000)/911000000 -> 2.3012569
D110: Dividend per preferred share | F110: Annual statement | G110: EUR | I110: =I108+0.01 -> 2.3112569
D112: Market equity value | F112: Calcs | G112: EUR | I112: =(I104+I106)*I102 -> 41313850000
D114: EV - Enterprise Value | F114: Calcs | G114: EUR | I114: =I112+(I96-I60+I88)*1000000 -> 47878850000
B116: Multiples | F116: Source | G116: UoM
D118: P/E (21.05.2026) | F118: Calcs | G118: Number | I118: =I102/I124 -> 94.479167
D120: P/E (31.12.2025) | F120: Calcs | G120: Number | I120: =I100/I124 -> 95.041667
D122: Basic earnings per ordinary share | F122: AS Note 12, page 360 (34) | G122: EUR | I122: 0.47
D124: Basic earnings per preferred share | F124: AS Note 12, page 360 (34) | G124: EUR | I124: 0.48
D126: EV/EBITDA | F126: Calcs | G126: Number | I126: =I114/(I43*1000000) -> 11.029452

Sheet Relative Valuation
B2: Relative Valuation
C4: As of 21.05.2026
C6: Peer | D6: EPS, € | E6: Share Price, € | F6: P/E | G6: Weight
C7: BMW | D7: =BMW!I124 -> 11.89 | E7: =BMW!I102 -> 74.11 | F7: =E7/D7 -> 6.2329689 | G7: =0.6 -> 0.6
C8: VW | D8: =VW!I122 -> 13.29 | E8: =VW!I102 -> 88.5 | F8: =E8/D8 -> 6.6591422 | G8: =0.35 -> 0.35
C9: Porsche | D9: =Porsche!I124 -> 0.48 | E9: =Porsche!I102 -> 45.35 | F9: =E9/D9 -> 94.479167 | G9: =1-G7-G8 -> 0.05
C10: Weighted | F10: =SUMPRODUCT(F7:F9,G7:G9) -> 10.794439
C12: Peer | D12: EV, mln € | E12: EBITDA, mln € | F12: EV/EBITDA | G12: Weight
C13: BMW | D13: =BMW!I116/1000000 -> 139306.39 | E13: =BMW!I43 -> 25208 | F13: =D13/E13 -> 5.526277 | G13: =0.5 -> 0.5
C14: VW | D14: =VW!I114/1000000 -> 285043.63 | E14: =VW!I43 -> 41128 | F14: =D14/E14 -> 6.9306465 | G14: =0.3 -> 0.3
C15: Porsche | D15: =Porsche!I114/1000000 -> 47878.85 | E15: =Porsche!I43 -> 4341 | F15: =D15/E15 -> 11.029452 | G15: =1-G13-G14 -> 0.2
C16: Weighted | F16: =SUMPRODUCT(F13:F15,G13:G15) -> 7.0482228
C18: As of 21.05.26 | D18: Earnings per share, € | E18: Implied Share Price, € | F18: EBITDA, mln € | G18: Implied EV, mln € | H18: Implied Equity Value, mln € | I18: Number of Shares Outstanding | J18: Implied Share Price, €
C19: Mercedes | D19: =PL!N65 -> 5.34 | E19: =D19*F10 -> 57.642307 | F19: =EBITDA!N18 -> 19204 | G19: =F19*F16 -> 135354.07 | H19: =G19-BS!N95-BS!N129+BS!N57-BS!N186 -> 46596.07 | I19: 962903703 | J19: =H19*1000000/I19 -> 48.391205
C22: As of 21.05.26 | D22: Implied Share Price, €
C23: Mercedes | D23: =0.7*J19+0.3*E19 -> 51.166535
C27: Real price | E27: =49.76 -> 49.76
C28: https://ru.investing.com/equities/daimler

Sheet 4. DCF

Sheet Beta
D1: Mercedes | F1: DAX 40 | K1: Sources
K2: Mercedes | L2: Adj Close | M2: https://finance.yahoo.com/quote/MBG.DE/history/?frequency=1mo&period1=846662400&period2=1779099298
C3: Date | D3: Price, EUR | E3: Return, % | F3: Price, EUR | G3: Return, % | K3: DAX 40 | L3: Adj Close | M3: https://finance.yahoo.com/quote/%5EGDAXI/history/?frequency=1mo&period1=567849600&period2=1779099298
C5: 46173 | D5: 50.349998 | E5: =D5/D6-1 -> 0.015428041 | F5: 23950.57 | G5: =F5/F6-1 -> -0.014070689 | K5: Observations
C6: 46142 | D6: 49.584999 | E6: =D6/D7-1 -> 0.012910737 | F6: 24292.381 | G6: =F6/F7-1 -> 0.071090786 | K6: n | L6: 120
C7: 46112 | D7: 48.95298 | E7: =D7/D8-1 -> -0.11203389 | F7: 22680.039 | G7: =F7/F8-1 -> -0.1029977 | K7: range | L7: 42400 | M7: 46022
C8: 46081 | D8: 55.129333 | E8: =D8/D9-1 -> 0.020937888 | F8: 25284.26 | G8: =F8/F9-1 -> 0.030378376
C9: 46053 | D9: 53.998714 | E9: =D9/D10-1 -> -0.037955701 | F9: 24538.811 | G9: =F9/F10-1 -> 0.0019762997 | K9: Calculation
C10: 46022 | D10: 56.129135 | E10: =D10/D11-1 -> 0.032840428 | F10: 24490.41 | G10: =F10/F11-1 -> 0.027420685 | K10: DAX Std | L10: =_xlfn.STDEV.S(G10:G129) -> 0.046804063
C11: 45991 | D11: 54.34444 | E11: =D11/D12-1 -> 0.034691334 | F11: 23836.789 | G11: =F11/F12-1 -> -0.0050718004 | K11: DAX Var | L11: =_xlfn.VAR.S(G10:G129) -> 0.0021906203
C12: 45961 | D12: 52.522369 | E12: =D12/D13-1 -> 0.04305065 | F12: 23958.301 | G12: =F12/F13-1 -> 0.0032486489 | K12: CoVar | L12: =_xlfn.COVARIANCE.S(G10:G129,E10:E129) -> 0.0029481961
C13: 45930 | D13: 50.354572 | E13: =D13/D14-1 -> 0.010121842 | F13: 23880.721 | G13: =F13/F14-1 -> -0.00089908981 | K13: Beta | L13: =L12/L11 -> 1.3458271 | M13: Unadjusted Beta is preferred over adjusted in further analysis to reflect company and market instability and industry EV disruption
C14: 45900 | D14: 49.849998 | E14: =D14/D15-1 -> 0.064870256 | F14: 23902.211 | G14: =F14/F15-1 -> -0.0067839839 | K14: Adj. Beta | L14: =L13*2/3+1/3 -> 1.2305514
C15: 45869 | D15: 46.813213 | E15: =D15/D16-1 -> 0.0082511631 | F15: 24065.471 | G15: =F15/F16-1 -> 0.0065187735
C16: 45838 | D16: 46.430111 | E16: =D16/D17-1 -> -0.055143572 | F16: 23909.609 | G16: =F16/F17-1 -> -0.00366168
C17: 45808 | D17: 49.139858 | E17: =D17/D18-1 -> 0.089021457 | F17: 23997.48 | G17: =F17/F18-1 -> 0.06669784
C18: 45777 | D18: 45.122948 | E18: =D18/D19-1 -> -0.031740202 | F18: 22496.98 | G18: =F18/F19-1 -> 0.015046828
C19: 45747 | D19: 46.602108 | E19: =D19/D20-1 -> -0.093357889 | F19: 22163.49 | G19: =F19/F20-1 -> -0.017202433
C20: 45716 | D20: 51.400776 | E20: =D20/D21-1 -> 0.014426421 | F20: 22551.43 | G20: =F20/F21-1 -> 0.037703708
C21: 45688 | D21: 50.669792 | E21: =D21/D22-1 -> 0.095167251 | F21: 21732.051 | G21: =F21/F22-1 -> 0.091561469
C22: 45657 | D22: 46.266716 | E22: =D22/D23-1 -> 0.015861064 | F22: 19909.141 | G22: =F22/F23-1 -> 0.014403594
C23: 45626 | D23: 45.544334 | E23: =D23/D24-1 -> -0.04919218 | F23: 19626.449 | G23: =F23/F24-1 -> 0.028772587
C24: 45596 | D24: 47.900673 | E24: =D24/D25-1 -> -0.040317025 | F24: 19077.539 | G24: =F24/F25-1 -> -0.012801631
C25: 45565 | D25: 49.913017 | E25: =D25/D26-1 -> -0.068976536 | F25: 19324.93 | G25: =F25/F26-1 -> 0.022108824
C26: 45535 | D26: 53.610912 | E26: =D26/D27-1 -> 0.01929363 | F26: 18906.92 | G26: =F26/F27-1 -> 0.021518021
... C359: 35399 | D359: 10.546446 | E359: =D359/D360-1 -> 0.12650812 | F359: 2848.8401 | G359: =F359/F360-1 -> 0.066422173
C360: 35369 | D360: 9.3620682 | E360: =D360/#REF!-1 -> #REF! | F360: 2671.3999 | G360: =F360/#REF!-1 -> #REF!

Sheet COE
H1: Rf | I1: 0.0315 | J1: (Germany 10Y Bonds)
H2: US 10Y Bonds | I2: 0.04656
H3: Default spread | I3: 0
H4: Inflation premium | I4: =((1+I5)/(1+I6))-1 -> 0 | K4: =I2+I3+I4 -> 0.04656
H5: Ger Inflation | I5: 0.02
H6: US Inflation target | I6: 0.02
H7: Beta | I7: =Beta!L13 -> 1.3458271 | J7: Illia's calculation | R7: https://curvo.eu/backtest/en/compare-indexes/cac-40-vs-dax?currency=eur
H8: Rm | I8: 0.086 | J8: DAX 40 avr last 10y return
H10: COE | I10: =I1+I7*(I8-I1) -> 0.10484757

Sheet COD
A1: Based on credit rating: | E1: Rf | F1: =COE!$I$1 -> 0.0315
E2: Credit Spread | F2: 0.0072
A3: S&P Rating | B3: A
A6: Rd = Rf + Credit spread | E6: COD | F6: =F1+F2 -> 0.0387
R16: https://pages.stern.nyu.edu/~adamodar/New_Home_Page/datafile/ctryprem.html

Sheet WACC
H1: Equity | I1: =BS!N191 -> 94263 | J1: mln. EUR
H2: Debt | I2: =BS!N95+BS!N129 -> 100006 | J2: mln. EUR
H3: D+E | I3: =SUM(I1:I2) -> 194269 | J3: mln. EUR
H4: COE | I4: =COE!I10 -> 0.10484757
H5: COD | I5: =COD!F6 -> 0.0387
H6: EBT | I6: 6248 | J6: mln. EUR | K6: from PnL
H7: T in EUR | I7: 953 | J7: mln. EUR
H8: T in % | I8: =I7/I6 -> 0.15252881
H9: Inncome tax | I9: 0.3
H11: WACC | I11: =((I1/I3)*I4)+((I2/I3)*I5*(1-I9)) -> 0.064819449

Sheet DCF
C1: Free Cash Flow to the Firm Model
C3: in mln of euros | D3: Source | E3: Comment | F3: 2021 | G3: =F3+1 -> 2022 | H3: =G3+1 -> 2023 | I3: =H3+1 -> 2024 | J3: 2025 | K3: =J3+1 -> 2026 | L3: =K3+1 -> 2027 | M3: =L3+1 -> 2028 | N3: =M3+1 -> 2029 | O3: =N3+1 -> 2030 | P3: =O3+1 -> 2031 | Q3: =P3+1 -> 2032 | R3: =Q3+1 -> 2033 | ... T3: =S3+1 -> 2035
C5: Revenue | D5: Link | F5: =PL!J11 -> 133893 | G5: =PL!K11 -> 150017 | H5: =PL!L11 -> 152390 | I5: =PL!M11 -> 145594 | J5: =PL!N11 -> 132214 | K5: =J5*(1+K6) -> 125735.51 | L5: =K5*(1+L6) -> 122592.13 | M5: =L5*(1+M6) -> 121979.17 | N5: =M5*(1+N6) -> 121979.17 | O5: =N5*(1+O6) -> 122101.14 | P5: =O5*(1+P6) -> 122345.35 | Q5: =P5*(1+Q6) -> 122712.38 | R5: =Q5*(1+R6) -> 123203.23 | ... T5: =S5*(1+T6) -> 124438.34
C6: Growth, % | D6: Calcs | E6: 2025 saw US tariffs and a 29% decline in China following another 27% decline in deliveries in 2026Q1 due to strong competition, the trend likely to continue in the following year. The company, however, is making progress in the EV sector with the success of the new Mercedes-Benz CLA, MB.OS and VAN.EA in 2026. | G6: =G5/F5-1 -> 0.12042452 | H6: =H5/G5-1 -> 0.015818207 | I6: =I5/H5-1 -> -0.044596102 | J6: =J5/I5-1 -> -0.091899391 | K6: =-4.9% -> -0.049 | L6: -0.025 | M6: -0.005 | N6: 0 | O6: 0.001 | P6: 0.002 | Q6: 0.003 | R6: 0.004 | S6: 0.005 | T6: 0.005
C8: EBITDA | D8: Link | F8: =EBITDA!J18 -> 28272 | G8: =EBITDA!K18 -> 30243 | H8: =EBITDA!L18 -> 29430 | I8: =EBITDA!M18 -> 25154 | J8: =EBITDA!N18 -> 19204 | K8: =K5*K9 -> 18860.327 | L8: =L5*L9 -> 18388.819 | M8: =M5*M9 -> 19516.666 | N8: =N5*N9 -> 19516.666 | O8: =O5*O9 -> 19536.183 | P8: =P5*P9 -> 19575.256 | Q8: =Q5*Q9 -> 20861.105 | R8: =R5*R9 -> 20944.55 | ... T8: =T5*T9 -> 21154.519
C9: EBITDA margin, % | D9: Calcs | E9: EBITDA margin took a hit due to tariffs and China headwinds, but is expected to gradually stabilise. | F9: =F8/F5 -> 0.21115368 | G9: =G8/G5 -> 0.20159715 | H9: =H8/H5 -> 0.19312291 | I9: =I8/I5 -> 0.17276811 | J9: =J8/J5 -> 0.14524937 | K9: 0.15 | L9: 0.15 | M9: 0.16 | N9: 0.16 | O9: 0.16 | P9: 0.16 | Q9: 0.17 | R9: 0.17 | S9: 0.17 | T9: 0.17
C11: Depreciation & amortization | D11: CFS | F11: =CF!J21 -> 6980 | G11: =CF!K21 -> 6521 | H11: =CF!L21 -> 6663 | I11: =CF!M21 -> 6772 | J11: =CF!N21 -> 7223 | K11: =J11+J12*5% -> 7710.1 | L11: =K11+K12*5% -> 8275.9098 | M11: =L11+L12*5% -> 8796.9263 | N11: =M11+M12*5% -> 9284.843 | O11: =N11+N12*5% -> 9711.7701 | P11: =O11+O12*5% -> 10078.074 | Q11: =P11+P12*5% -> 10414.523 | R11: =Q11+Q12*5% -> 10751.982 | ... T11: =S11+S12*5% -> 11369.538
C12: CAPEX (IAS 17) | D12: CFS | E12: Further expenditures are expected in 2026-28 with the continued EV transition, stabilising further on. | F12: =-1*SUM(CF!J44:J45) -> 7320 | G12: =-1*SUM(CF!K44:K45) -> 6899 | H12: =-1*SUM(CF!L44:L45) -> 8213 | I12: =-1*SUM(CF!M44:M45) -> 8665 | J12: =-1*SUM(CF!N44:N45) -> 9742 | K12: =K5*K13 -> 11316.196 | L12: =L5*L13 -> 10420.331 | M12: =M5*M13 -> 9758.3332 | N12: =N5*N13 -> 8538.5416 | O12: =O5*O13 -> 7326.0687 | P12: =P5*P13 -> 6728.9941 | Q12: =Q5*Q13 -> 6749.1811 | R12: =R5*R13 -> 6160.1616 | ... T12: =T5*T13 -> 6221.9172
C13: CAPEX (IAS 17) margin, % | D13: Calcs | F13: =F12/F5 -> 0.05467052 | G13: =G12/G5 -> 0.045988121 | H13: =H12/H5 -> 0.053894613 | I13: =I12/I5 -> 0.059514815 | J13: =J12/J5 -> 0.073683574 | K13: 0.09 | L13: 0.085 | M13: 0.08 | N13: 0.07 | O13: 0.06 | P13: 0.055 | Q13: 0.055 | R13: 0.05 | S13: 0.05 | T13: 0.05
C15: Interest paid | D15: Note 29 | E15: In 2024 Mercedes adjusted interest paid for 2023 from 324 to 3068 while not providing notes about the motivation for the adjustment. We accept it and believe that the approach to accounting was changed and will remain the same in the foreseeable future. | F15: 367 | G15: 486 | H15: 3068 | I15: 3902 | J15: 4003 | K15: =K17*K16 -> 4065.8041 | L15: =L17*L16 -> 3743.9279 | M15: =M17*M16 -> 3005.21 | N15: =N17*N16 -> 2191.299 | O15: =O17*O16 -> 1880.1345 | P15: =P17*P16 -> 1381.5229 | Q15: =Q17*Q16 -> 1385.6674 | R15: =R17*R16 -> 1264.7364 | ... T15: =T17*T16 -> 1277.4154
C16: Effective interest rate | D16: Bundesbank IR | E16: According to Bundesbank, interest rates are to remain unchanged from 2025, inflation projected to stabilise around 2%. Geopolitical pressure and energy logistics are expected to stabilise further during the later half of the forecast period. | G16: =G15/(F17+G17)*2 -> 0.0040895321 | H16: =H15/(G17+H17)*2 -> 0.027731077 | I16: =I15/(H17+I17)*2 -> 0.035116929 | J16: =J15/(I17+J17)*2 -> 0.037621473 | K16: 0.035 | L16: 0.035 | M16: 0.03 | N16: 0.025 | O16: 0.025 | P16: 0.02 | Q16: 0.02 | R16: 0.02 | S16: 0.02 | T16: 0.02
C17: Debt | D17: Link | E17: Expected to increase to fuel CAPEX required for continued EV transition. | F17: =BS!J95+BS!J129 -> 125843 | G17: =BS!K95+BS!K129 -> 111837 | H17: =BS!L95+BS!L129 -> 109431 | I17: =BS!M95+BS!M129 -> 112798 | J17: =BS!N95+BS!N129 -> 100006 | K17: =J17*(1+K18) -> 116165.83 | L17: =K17*(1+L18) -> 106969.37 | M17: =L17*(1+M18) -> 100173.67 | N17: =M17*(1+N18) -> 87651.96 | O17: =N17*(1+O18) -> 75205.381 | P17: =O17*(1+P18) -> 69076.143 | Q17: =P17*(1+Q18) -> 69283.371 | R17: =Q17*(1+R18) -> 63236.822 | ... T17: =S17*(1+T18) -> 63870.772
C18: Growth, % | E18: Calculated based on CAPEX changes. | G18: =G12/F12-1 -> -0.057513661 | H18: =H12/G12-1 -> 0.19046239 | I18: =I12/H12-1 -> 0.055034701 | J18: =J12/I12-1 -> 0.12429313 | K18: =K12/J12-1 -> 0.16158861 | L18: =L12/K12-1 -> -0.079166667 | M18: =M12/L12-1 -> -0.063529412 | N18: =N12/M12-1 -> -0.125 | ... T18: =T12/S12-1 -> 0.005
C19: Net change in borrowings | D19: Calcs | G19: =G17-F17 -> -14006 | H19: =H17-G17 -> -2406 | I19: =I17-H17 -> 3367 | J19: =J17-I17 -> -12792 | K19: =K17-J17 -> 16159.831 | L19: =L17-K17 -> -9196.4616 | M19: =M17-L17 -> -6795.7011 | N19: =N17-M17 -> -12521.709 | ... T19: =T17-S17 -> 317.76503
C21: Profit before tax | D21: Link | F21: =PL!J46 -> 15811 | G21: =PL!K46 -> 20304 | H21: =PL!L46 -> 20084 | I21: =PL!M46 -> 14147 | J21: =PL!N46 -> 6284 | K21: =K8-K11-K15 -> 7084.423 | L21: =L8-L11-L15 -> 6368.9812 | M21: =M8-M11-M15 -> 7714.5301 | N21: =N8-N11-N15 -> 8040.5245 | O21: =O8-O11-O15 -> 7944.2785 | P21: =P8-P11-P15 -> 8115.6591 | Q21: =Q8-Q11-Q15 -> 9060.9145 | R21: =R8-R11-R15 -> 8927.8308 | ... T21: =T8-T11-T15 -> 8507.5647
C22: Effective tax rate | D22: Note 10 | E22: According to PwC, German corporate tax rate is planned to decrease from 15% to 10% by 1% a year starting in 2028 and completing in 2032. 0.5% decrease is calculated assuming 40% of Mercedes-Benz Group AG profits are subject to German tax. | F22: =-1*PL!J49/PL!J46 -> 0.30111947 | G22: =-1*PL!K49/PL!K46 -> 0.27063633 | H22: =-1*PL!L49/PL!L46 -> 0.27648875 | I22: =-1*PL!M49/PL!M46 -> 0.26422563 | J22: =-1*PL!N49/PL!N46 -> 0.151655 | K22: 0.3 | L22: =K22 -> 0.3 | M22: =L22-0.5% -> 0.295 | N22: =M22-0.5% -> 0.29 | O22: =N22-0.5% -> 0.285 | P22: =O22-0.5% -> 0.28 | Q22: =P22-0.5% -> 0.275 | R22: =Q22 -> 0.275 | S22: =R22 -> 0.275 | T22: =S22 -> 0.275
C24: Net working capital | D24: Calcs | F24: =F25-F26 -> 52154 | G24: =G25-G26 -> 58829 | H24: =H25-H26 -> 60189 | I24: =I25-I26 -> 61544 | J24: =J25-J26 -> 54117 | K24: =K5/365*K27 -> 50511.958 | L24: =L5/365*L27 -> 49249.159 | M24: =M5/365*M27 -> 49002.914 | N24: =N5/365*N27 -> 49002.914 | O24: =O5/365*O27 -> 49051.916 | P24: =P5/365*P27 -> 49150.02 | Q24: =Q5/365*Q27 -> 49297.47 | R24: =R5/365*R27 -> 49494.66 | ... T24: =T5/365*T27 -> 49990.844
C25: Adj Current assets (operational) | D25: Link | F25: =BS!J48+BS!J51+BS!J54+BS!J66 -> 62809 | G25: =BS!K48+BS!K51+BS!K54+BS!K66 -> 71033 | H25: =BS!L48+BS!L51+BS!L54+BS!L66 -> 73842 | I25: =BS!M48+BS!M51+BS!M54+BS!M66 -> 73561 | J25: =BS!N48+BS!N51+BS!N54+BS!N66 -> 65428
C26: Adj Current liabilities (operational) | D26: Link | F26: =BS!J123+BS!J141 -> 10655 | G26: =BS!K123+BS!K141 -> 12204 | H26: =BS!L123+BS!L141 -> 13653 | I26: =BS!M123+BS!M141 -> 12017 | J26: =BS!N123+BS!N141 -> 11311
C27: NWC turnover, days | D27: Calcs | F27: =F24/F5*365 -> 142.1748 | G27: =G24/G5*365 -> 143.13434 | H27: =H24/H5*365 -> 144.1629 | I27: =I24/I5*365 -> 154.28905 | J27: =J24/J5*365 -> 149.3995 | K27: =AVERAGE(F27:J27) -> 146.63212 | L27: =K27 -> 146.63212 | M27: =L27 -> 146.63212 | N27: =M27 -> 146.63212 | O27: =N27 -> 146.63212 | P27: =O27 -> 146.63212 | Q27: =P27 -> 146.63212 | R27: =Q27 -> 146.63212 | S27: =R27 -> 146.63212 | T27: =S27 -> 146.63212
C28: Δ NWC | D28: Calcs | G28: =G25-F25 -> 8224 | H28: =H25-G25 -> 2809 | I28: =I25-H25 -> -281 | J28: =J25-I25 -> -8133 | K28: =K24-J24 -> -3605.0417 | L28: =L24-K24 -> -1262.799 | M28: =M24-L24 -> -246.2458 | N28: =N24-M24 -> 0 | O28: =O24-N24 -> 49.002914 | P28: =P24-O24 -> 98.103833 | Q28: =Q24-P24 -> 147.45006 | R28: =R24-Q24 -> 197.18988 | ... T28: =T24-S24 -> 248.71067
C31: EBIT * (1-tax) | K31: =(K8-K11)*(1-K22) -> 7805.159 | L31: =(L8-L11)*(1-L22) -> 7079.0364 | M31: =(M8-M11)*(1-M22) -> 7557.4168 | N31: =(N8-N11)*(1-N22) -> 7264.5947 | O31: =(O8-O11)*(1-O22) -> 7024.4553 | P31: =(P8-P11)*(1-P22) -> 6837.971 | Q31: =(Q8-Q11)*(1-Q22) -> 7573.7719 | R31: =(R8-R11)*(1-R22) -> 7389.6113 | ... T31: =(T8-T11)*(1-T22) -> 7094.1106
C32: Depreciation | K32: =K11 -> 7710.1 | L32: =L11 -> 8275.9098 | M32: =M11 -> 8796.9263 | N32: =N11 -> 9284.843 | O32: =O11 -> 9711.7701 | P32: =P11 -> 10078.074 | Q32: =Q11 -> 10414.523 | R32: =R11 -> 10751.982 | ... T32: =T11 -> 11369.538
C33: Δ NWC | K33: =-K28 -> 3605.0417 | L33: =-L28 -> 1262.799 | M33: =-M28 -> 246.2458 | N33: =-N28 -> 0 | O33: =-O28 -> -49.002914 | P33: =-P28 -> -98.103833 | Q33: =-Q28 -> -147.45006 | R33: =-R28 -> -197.18988 | ... T33: =-T28 -> -248.71067
C34: CAPEX | K34: =-K12 -> -11316.196 | L34: =-L12 -> -10420.331 | M34: =-M12 -> -9758.3332 | N34: =-N12 -> -8538.5416 | O34: =-O12 -> -7326.0687 | P34: =-P12 -> -6728.9941 | Q34: =-Q12 -> -6749.1811 | R34: =-R12 -> -6160.1616 | ... T34: =-T12 -> -6221.9172
C35: Free Cash Flow to the Firm | K35: =SUM(K31:K34) -> 7804.1044 | L35: =SUM(L31:L34) -> 6197.4144 | M35: =SUM(M31:M34) -> 6842.2557 | N35: =SUM(N31:N34) -> 8010.8961 | O35: =SUM(O31:O34) -> 9361.1538 | P35: =SUM(P31:P34) -> 10088.947 | Q35: =SUM(Q31:Q34) -> 11091.664 | R35: =SUM(R31:R34) -> 11784.242 | ... T35: =SUM(T31:T34) -> 11993.021
C37: Discount rate (WACC) | D37: =WACC!I11 -> 0.064819449
C38: Discount factor | J38: 1 | K38: =J38/(1+$D$37) -> 0.93912635 | L38: =K38/(1+$D$37) -> 0.8819583 | M38: =L38/(1+$D$37) -> 0.82827027 | N38: =M38/(1+$D$37) -> 0.77785044 | O38: =N38/(1+$D$37) -> 0.73049984 | P38: =O38/(1+$D$37) -> 0.68603165 | Q38: =P38/(1+$D$37) -> 0.6442704 | R38: =Q38/(1+$D$37) -> 0.6050513 | ... T38: =S38/(1+$D$37) -> 0.53363002
C39: Discounted FCFF | K39: =K35*K38 -> 7329.0401 | L39: =L35*L38 -> 5465.8611 | M39: =M35*M38 -> 5667.237 | N39: =N35*N38 -> 6231.279 | O39: =O35*O38 -> 6838.3214 | P39: =P35*P38 -> 6921.3367 | Q39: =Q35*Q38 -> 7146.0307 | R39: =R35*R38 -> 7130.071 | ... T39: =T35*T38 -> 6399.8361
C40: Long-term growth rate | D40: 0.006 | E40: Germany GDP growth rate
C41: Terminal value | T41: =T35*(1+D40)/(D37-D40)*T38 -> 109457.59
C43: Enterprise value | D43: =SUM(K39:T39)+T41 -> 175327.84
C44: Net debt | D44: =Ratios!D7 -> 88640 | E44: As of 31/12/25
C45: Estimated Equity value | D45: =D43-D44 -> 86687.839
C46: Number of shares, mln | D46: =Ratios!D4 -> 962.9037
C47: Estimated share value | D47: =D45/D46 -> 90.027527 | E47: EUR
C49: Free Cash Flow to Equity | K49: =K35-K15*(1-K22)+K19 -> 21117.872 | L49: =L35-L15*(1-L22)+L19 -> -5619.7967 | M49: =M35-M15*(1-M22)+M19 -> -2072.1185 | N49: =N35-N15*(1-N22)+N19 -> -6066.6347 | O49: =O35-O15*(1-O22)+O19 -> -4429.7206 | P49: =P35-P15*(1-P22)+P19 -> 2965.0116 | Q49: =Q35-Q15*(1-Q22)+Q19 -> 10294.284 | R49: =R35-R15*(1-R22)+R19 -> 4820.7594 | ... T49: =T35-T15*(1-T22)+T19 -> 11384.66
C51: Discount rate (Re) | D51: =COE!I10 -> 0.10484757
C52: Discount factor | J52: 1 | K52: =J52/(1+$D$51) -> 0.90510223 | L52: =K52/(1+$D$51) -> 0.81921004 | M52: =L52/(1+$D$51) -> 0.74146883 | N52: =M52/(1+$D$51) -> 0.67110509 | O52: =N52/(1+$D$51) -> 0.60741871 | P52: =O52/(1+$D$51) -> 0.54977603 | Q52: =P52/(1+$D$51) -> 0.49760351 | R52: =Q52/(1+$D$51) -> 0.45038204 | ... T52: =S52/(1+$D$51) -> 0.36895749
C53: Discounted FCFF | K53: =K49*K52 -> 19113.833 | L53: =L49*L52 -> -4603.7939 | M53: =M49*M52 -> -1536.4113 | N53: =N49*N52 -> -4071.3494 | O53: =O49*O52 -> -2690.6952 | P53: =P49*P52 -> 1630.0923 | Q53: =Q49*Q52 -> 5122.4716 | R53: =R49*R52 -> 2171.1834 | ... T53: =T49*T52 -> 4200.4556
C54: Long-term growth rate | D54: =D40 -> 0.006
C55: Terminal value | T55: =T49*(1+D54)/(D51-D54)*T52 -> 42749.237
C57: Estimated Equity value | D57: =SUM(K53:T53)+T55+Ratios!D5 -> 78928.438 | E57: With cash and cash equivalents added back
C58: Number of shares, mln | D58: =D46 -> 962.9037
C59: Estimated share value | D59: =D57/D58 -> 81.969191 | E59: EUR
C60: Current market price | D60: =Ratios!D3 -> 52.19 | E60: EUR
C61: Implied upside | D61: =D59/D60-1 -> 0.5705919

Sheet 5. DDM

Sheet Dividend Policy Summary
A1: Financial Year | B1: Dividend per Share (EUR) | C1: YoY Change | D1: Payout Ratio (%) | E1: Target Payout Ratio (%) | F1: Difference vs Target | G1: Event / Note | I1: Фаза I — «Эра Daimler-Chrysler / ранний Daimler» (2002–2010) В 2002–2008 годах дивиденд оставался стабильным в диапазоне €1,0–2,0/акц., фактически «замороженным» на €1,50 в 2003–2007 годах. Это классическая политика стабильного номинального дивиденда, характерная для крупных немецких промышленных концернов с более широким периметром бизнеса. В 2009 году, в разгар финансового кризиса, дивиденд рухнул с €2,00 до €0,60 — снижение на 70%. В 2010 году выплачен €1,85 — символичное восстановление на фоне быстрого возврата прибыльности. ​ Фаза II — «Рост и стабилизация» (2011–2018) В 2011–2018 годах дивиденд восстановился и рос в целом умеренно, достигнув €3,65 в 2017 году — исторического рекорда той эпохи. Payout ratio в этот период находился вблизи 35–45%, что ретроспективно совпадает с нынешним целевым ориентиром ~40%. Политика оставалась предсказуемой и последовательной: дивиденды либо росли, либо оставались на прежнем уровне. ​ Фаза III — «COVID и коллапс» (2019–2020) Это наиболее показательный кризисный эпизод в новейшей истории. Дивиденд за FY2018 был снижен до €3,25. За FY2019 компания первоначально объявила €3,25, однако в апреле 2020 года, в самый острый момент пандемии, выплата была отменена — беспрецедентное решение. Вместо него в июле 2020 года выплачен уменьшенный дивиденд €0,90/акц. — официальный дивиденд за FY2019. За FY2020 выплачено €1,35. Фаза IV — «Рекордная прибыль и рекордные дивиденды» (2021–2023) Выделение Daimler Truck в декабре 2021 года и концентрация бизнеса на люксовом сегменте дали взрывной рост рентабельности. Net income по итогам FY2021 составила €23,4 млрд. Дивиденд за FY2021 был установлен на уровне €5,00/акц. — рост +270%. Несмотря на то что payout ratio при этом составил лишь ~12% (прибыль была исключительно высокой в том числе за счёт разовых эффектов), менеджмент принял решение направить значительный объём прибыли в buyback, а не завышать дивиденд. В 2022–2023 годах дивиденд достиг пика на уровне €5,20 и €5,30 соответственно. Фаза V — «Цикличный спад» (2024–2025) В 2024 году прибыль начала снижаться под давлением тарифов, конкуренции китайских производителей и ослабления спроса. Дивиденд за FY2024 снижен до €4,30 (−18,9%), однако payout ratio точно соответствовал ориентиру ~41%. По итогам FY2025, на фоне падения чистой прибыли на 48,8% до €5,33 млрд, дивиденд снижен до €3,50 (−18,6%). При этом payout ratio вырос до ~80%, что свидетельствует о желании менеджмента сохранить абсолютный уровень выплат и не пугать инвесторов резкими сокращениями — сознательное отступление от ориентира в 40%. | V1: Mercedes-Benz Group AG (Frankfurt: MBG) придерживается официально задокументированной гибкой дивидендной политики с целевым ориентиром ~40% от чистой прибыли, атрибутируемой акционерам. Политика дополнена систематическими программами выкупа акций, превращая совокупные акционерные выплаты (TSR) в один из ключевых KPI менеджмента. За последние 23 года компания прошла через три ощутимых дивидендных цикла, отражающих глубину и природу кризисов: в 2009 году (финансовый кризис), в 2019–2020 годах (COVID) и в текущем цикле 2024–2025 годов (снижение прибыли под давлением тарифов, конкуренции Китая и цикличности спроса). Начиная с 2022 года, Mercedes-Benz систематически дополняет дивиденды масштабными программами обратного выкупа акций. Все выкупленные акции аннулируются, что увеличивает EPS для оставшихся акционеров. В 2025 году совокупный total shareholder return превысил 20%, несмотря на падение прибыли на 48,8%. Это достигнуто за счёт сочетания дивиденда €4,1 млрд (FY2024, выплачен в 2025) и активного buyback
A2: 2002 | B2: 1 | E2: 40 | F2: =IF(D2="","",D2-E2)
A3: 2003 | B3: 1.5 | C3: =IFERROR(B3/B2-1,"") -> 0.5 | E3: 40 | F3: =IF(D3="","",D3-E3)
A4: 2004 | B4: 1.5 | C4: =IFERROR(B4/B3-1,"") -> 0 | E4: 40 | F4: =IF(D4="","",D4-E4)
A5: 2005 | B5: 1.5 | C5: =IFERROR(B5/B4-1,"") -> 0 | E5: 40 | F5: =IF(D5="","",D5-E5)
A6: 2006 | B6: 1.5 | C6: =IFERROR(B6/B5-1,"") -> 0 | E6: 40 | F6: =IF(D6="","",D6-E6)
A7: 2007 | B7: 1.5 | C7: =IFERROR(B7/B6-1,"") -> 0 | E7: 40 | F7: =IF(D7="","",D7-E7)
A8: 2008 | B8: 2 | C8: =IFERROR(B8/B7-1,"") -> 0.33333333 | E8: 40 | F8: =IF(D8="","",D8-E8)
A9: 2009 | B9: 0.6 | C9: =IFERROR(B9/B8-1,"") -> -0.7 | E9: 40 | F9: =IF(D9="","",D9-E9) | G9: Financial crisis
A10: 2010 | B10: 1.85 | C10: =IFERROR(B10/B9-1,"") -> 2.0833333 | E10: 40 | F10: =IF(D10="","",D10-E10)
A11: 2011 | B11: 2.2 | C11: =IFERROR(B11/B10-1,"") -> 0.18918919 | E11: 40 | F11: =IF(D11="","",D11-E11)
A12: 2012 | B12: 2.2 | C12: =IFERROR(B12/B11-1,"") -> 0 | E12: 40 | F12: =IF(D12="","",D12-E12)
A13: 2013 | B13: 2.25 | C13: =IFERROR(B13/B12-1,"") -> 0.022727273 | E13: 40 | F13: =IF(D13="","",D13-E13)
A14: 2014 | B14: 2.45 | C14: =IFERROR(B14/B13-1,"") -> 0.088888889 | E14: 40 | F14: =IF(D14="","",D14-E14)
A15: 2015 | B15: 3.25 | C15: =IFERROR(B15/B14-1,"") -> 0.32653061 | E15: 40 | F15: =IF(D15="","",D15-E15)
A16: 2016 | B16: 3.25 | C16: =IFERROR(B16/B15-1,"") -> 0 | E16: 40 | F16: =IF(D16="","",D16-E16)
A17: 2017 | B17: 3.65 | C17: =IFERROR(B17/B16-1,"") -> 0.12307692 | D17: 37 | E17: 40 | F17: =IF(D17="","",D17-E17) -> -3
A18: 2018 | B18: 3.25 | C18: =IFERROR(B18/B17-1,"") -> -0.10958904 | D18: 43 | E18: 40 | F18: =IF(D18="","",D18-E18) -> 3
A19: 2019 | B19: 0.9 | C19: =IFERROR(B19/B18-1,"") -> -0.72307692 | E19: 40 | F19: =IF(D19="","",D19-E19) | G19: COVID-19 / weak year
A20: 2020 | B20: 1.35 | C20: =IFERROR(B20/B19-1,"") -> 0.5 | E20: 40 | F20: =IF(D20="","",D20-E20) | G20: COVID-19
A21: 2021 | B21: 5 | C21: =IFERROR(B21/B20-1,"") -> 2.7037037 | E21: 40 | F21: =IF(D21="","",D21-E21) | G21: Post-COVID recovery
A22: 2022 | B22: 5.2 | C22: =IFERROR(B22/B21-1,"") -> 0.04 | D22: 42 | E22: 40 | F22: =IF(D22="","",D22-E22) -> 2 | G22: Rebrand: Mercedes-Benz Group
A23: 2023 | B23: 5.3 | C23: =IFERROR(B23/B22-1,"") -> 0.019230769 | D23: 50 | E23: 40 | F23: =IF(D23="","",D23-E23) -> 10
A24: 2024 | B24: 4.3 | C24: =IFERROR(B24/B23-1,"") -> -0.18867925 | D24: 41 | E24: 40 | F24: =IF(D24="","",D24-E24) -> 1
A25: 2025 | B25: 3.5 | C25: =IFERROR(B25/B24-1,"") -> -0.18604651 | D25: 80 | E25: 40 | F25: =IF(D25="","",D25-E25) -> 40 | G25: paid in April 2026

Sheet Technical Page for DPS
A1: Mercedes-Benz Group AG — Dividend History
A3: Metric | B3: Value | J3: Financial Year | K3: Dividend per Share (EUR) | L3: Payout Ratio (%) | M3: Target Payout Ratio (%)
A4: Latest FY in chart | B4: 2025 | J4: 2002 | K4: 1 | M4: 40
A5: Latest dividend per share | B5: =_xlfn.XLOOKUP(B4,'Dividend Policy Summary'!A:A,'Dividend Policy Summary'!B:B) -> 3.5 | J5: 2003 | K5: 1.5 | M5: 40
A6: Max dividend per share | B6: =MAX('Dividend Policy Summary'!B2:B25) -> 5.3 | J6: 2004 | K6: 1.5 | M6: 40
A7: Min dividend per share | B7: =MIN('Dividend Policy Summary'!B2:B25) -> 0.6 | J7: 2005 | K7: 1.5 | M7: 40
A8: Average dividend per share | B8: =AVERAGE('Dividend Policy Summary'!B2:B25) -> 2.5416667 | J8: 2006 | K8: 1.5 | M8: 40
J9: 2007 | K9: 1.5 | M9: 40
J10: 2008 | K10: 2 | M10: 40
J11: 2009 | K11: 0.6 | M11: 40
J12: 2010 | K12: 1.85 | M12: 40
J13: 2011 | K13: 2.2 | M13: 40
J14: 2012 | K14: 2.2 | M14: 40
J15: 2013 | K15: 2.25 | M15: 40
J16: 2014 | K16: 2.45 | M16: 40
J17: 2015 | K17: 3.25 | M17: 40
J18: 2016 | K18: 3.25 | M18: 40
J19: 2017 | K19: 3.65 | L19: 37 | M19: 40
J20: 2018 | K20: 3.25 | L20: 43 | M20: 40
J21: 2019 | K21: 0.9 | M21: 40
J22: 2020 | K22: 1.35 | M22: 40
J23: 2021 | K23: 5 | M23: 40
J24: 2022 | K24: 5.2 | L24: 42 | M24: 40
J25: 2023 | K25: 5.3 | L25: 50 | M25: 40
J26: 2024 | K26: 4.3 | L26: 41 | M26: 40
J27: 2025 | K27: 3.5 | L27: 80 | M27: 40

Sheet DDM
A1: Data | D1: VALUATION | Q1: SENSITIVITY ANALYSIS
A2: Rf | B2: 0.0315 | C2: Return on Germany 10Y Bonds | D2: I. One-Stage DDM (Baseline) | E2: For companies whose business and dividends are already very stable and have entered the mature stage. | S2: current Cost of Equity
A3: Market return | B3: 0.086 | C3: DAX 40 avg last 10y return | R3: =$J$16 -> 51.692697 | S3: =T3-0.5% -> 0.089847574 | T3: =U3-0.5% -> 0.094847574 | U3: =V3-0.5% -> 0.099847574 | V3: 0.10484757 | W3: =V3+0.5% -> 0.10984757 | X3: =W3+0.5% -> 0.11484757 | Y3: =X3+0.5% -> 0.11984757 | Z3: =Y3+0.5% -> 0.12484757
A4: Beta | B4: =Beta!L13 -> 1.3458271 | D4: Fact | J4: Forecast | Q4: terminal Growth | R4: =R5-0.5% -> 0.005 | S4: 50.932511 | T4: 48.098126 | U4: 45.562578 | V4: 43.280971 | W4: 41.216976 | X4: 39.340878 | Y4: 37.628135 | Z4: 36.058302
A5: Cost of Equity | B5: =B2+B4*(B3-B2) -> 0.10484757 | D5: Year | E5: 2021 | F5: 2022 | G5: 2023 | H5: 2024 | I5: 2025 | J5: 2026 | K5: 2027 | L5: 2028 | M5: 2029 | N5: 2030 | O5: 2032 | R5: =R6-0.5% -> 0.01 | S5: 54.391132 | T5: 51.185906 | U5: 48.337421 | V5: 45.789257 | W5: 43.496299 | X5: 41.422036 | Y5: 39.536604 | Z5: 37.815339
A6: Number of shares (million) | B6: =Ratios!D4 -> 962.9037 | D6: Period | I6: 0 | J6: 1 | K6: 2 | L6: 3 | M6: 4 | N6: 5 | O6: Terminal | R6: =R7-0.5% -> 0.015 | S6: 58.311843 | T6: 54.660395 | U6: 51.439302 | V6: 48.576715 | W6: 46.015937 | X6: 43.711628 | Y6: 41.627096 | Z6: 39.732329
A7: Last dividend per share (DPS₀) | B7: =I9 -> 4.3 | D7: EPS | E7: 9.96 | F7: 13.55 | G7: 13.46 | H7: =PL!$M$65 -> 10.19 | I7: =PL!$N$65 -> 5.34 | J7: =J9/J8 -> 10.965 | K7: =K9/K8 -> 11.1843 | L7: =L9/L8 -> 11.407986 | M7: =M9/M8 -> 11.636146 | N7: =N9/N8 -> 11.868869 | R7: 0.02 | S7: 62.793877 | T7: 58.599093 | U7: 54.929659 | V7: 51.692697 | W7: 48.816009 | X7: 46.242616 | Y7: 43.926956 | Z7: 41.832155
A8: One‑stage DDM | D8: Payout | E8: =E9/E7 -> 0.13554217 | F8: =F9/F7 -> 0.36900369 | G8: =G9/G7 -> 0.38632987 | H8: =H9/H7 -> 0.52011776 | I8: =I9/I7 -> 0.80524345 | J8: 0.4 | K8: 0.4 | L8: 0.4 | M8: 0.4 | N8: 0.4 | R8: =R7+0.5% -> 0.025 | S8: 67.967076 | T8: 63.10169 | U8: 58.886344 | V8: 55.198922 | W8: 51.946093 | X8: 49.055303 | Y8: 46.469296 | Z8: 44.142284
A9: Sustainable growth rate (g) | B9: 0.02 | C9: According to forecasts from the IMF, Germany's real GDP growth rate in 2026 is projected to be between 0.6% and 1.1%, with a similar growth rate for the Eurozone. Therefore, in the model, we will set a perpetual growth rate of 2% - it is a conservative estimate, which corresponds well with the projected 2% inflation and 1.81% market-implied company growth rate (calculated using inverse DDM), and is far lower than the expected long-term nominal GDP growth rate, providing a robust underlying assumption for DDM valuation. | D9: Dividends | E9: 1.35 | F9: 5 | G9: 5.2 | H9: 5.3 | I9: 4.3 | J9: =$I$9*(1+$B$9)^J6 -> 4.386 | K9: =$I$9*(1+$B$9)^K6 -> 4.47372 | L9: =$I$9*(1+$B$9)^L6 -> 4.5631944 | M9: =$I$9*(1+$B$9)^M6 -> 4.6544583 | N9: =$I$9*(1+$B$9)^N6 -> 4.7475475 | O9: =N9*(1+B9) -> 4.8424984 | R9: =R8+0.5% -> 0.03 | S9: 74.00467 | T9: 68.298622 | U9: 63.409503 | V9: 59.173594 | W9: 55.468185 | X9: 52.199489 | Y9: 49.294597 | Z9: 46.695975
A10: Intrinsic value per share | B10: =J16 -> 51.692697 | D10: Dividends Growth YoY | F10: =F9/E9-1 -> 2.7037037 | G10: =G9/F9-1 -> 0.04 | H10: =H9/G9-1 -> 0.019230769 | I10: =I9/H9-1 -> -0.18867925 | J10: =J9/I9-1 -> 0.02 | K10: =K9/J9-1 -> 0.02 | L10: =L9/K9-1 -> 0.02 | M10: =M9/L9-1 -> 0.02 | N10: =N9/M9-1 -> 0.02 | R10: =R9+0.5% -> 0.035 | S10: 81.143059 | T10: 74.363916 | U10: 68.630169 | V10: 63.717316 | W10: 59.460845 | X10: 55.737448 | Y10: 52.452884 | Z10: 49.533891
A11: Two‑stage DDM | D11: Discount factor | J11: =(1+$B$5)^(-J6) -> 0.90510223 | K11: =(1+$B$5)^(-K6) -> 0.81921004 | L11: =(1+$B$5)^(-L6) -> 0.74146883 | M11: =(1+$B$5)^(-M6) -> 0.67110509 | N11: =(1+$B$5)^(-N6) -> 0.60741871 | R11: =R10+0.5% -> 0.04 | S11: 89.713492 | T11: 81.535055 | U11: 74.723162 | V11: 68.961716 | W11: 64.025129 | X11: 59.748095 | Y11: 56.006711 | Z11: 52.70628
A12: High growth period (years) | B12: 5 | D12: PV of dividends | J12: =J9*J11 -> 3.9697784 | K12: =K9*K11 -> 3.6649163 | L12: =L9*L11 -> 3.3834664 | M12: =M9*M11 -> 3.1236307 | N12: =N9*N11 -> 2.8837492 | R12: =R11+0.5% -> 0.045 | S12: 100.19494 | T12: 90.144807 | U12: 81.92705 | V12: 75.082408 | W12: 69.293262 | X12: 64.332943 | Y12: 60.035346 | Z12: 56.275974
A13: High growth rate (g₁) | B13: 0.05 | D13: Sum of PV of dividends | J13: =SUM(J12:N12) -> 17.025541
A14: Terminal growth rate (g₂) | B14: =B9 -> 0.02 | D14: Terminal Value | N14: =O9/($B$5-$B$9) -> 57.072915
A15: Intrinsic value per share | B15: =J32 -> 58.576358 | D15: PV of Terminal Value | J15: =N14/(1+$B$5)^N6 -> 34.667157
A16: H-model | D16: Total PV | J16: =J13+J15 -> 51.692697
A17: Long-term growth rate (gl) | B17: =B14 -> 0.02
A18: Short-term growth rate (gs) | B18: =B13 -> 0.05 | D18: II. Two-Stage DDM | E18: For companies currently experiencing high growth but will return to stable growth in the future, better matching the cyclical nature of the automotive industry.
A19: High growth period (n) | B19: 5
A20: Intrinsic value per share | B20: =J48 -> 55.940897 | D20: Fact | J20: Forecast | S20: High Growth
A21: Comparison | D21: Year | E21: 2021 | F21: 2022 | G21: 2023 | H21: 2024 | I21: 2025 | J21: 2026 | K21: 2027 | L21: 2028 | M21: 2029 | N21: 2030 | O21: 2032 | R21: =$J$32 -> 58.576358 | S21: =T21-0.5% -> 0.035 | T21: =U21-0.5% -> 0.04 | U21: =V21-0.5% -> 0.045 | V21: 0.05 | W21: =V21+0.5% -> 0.055 | X21: =W21+0.5% -> 0.06 | Y21: =X21+0.5% -> 0.065 | Z21: =Y21+0.5% -> 0.07
A22: Current market price | B22: =Ratios!D3 -> 52.19 | D22: Period | I22: 0 | J22: 1 | K22: 2 | L22: 3 | M22: 4 | N22: 5 | O22: Terminal | Q22: Terminal (low) Growth | R22: =R23-0.5% -> 0.005 | S22: 48.974069 | T22: 49.98319 | U22: 51.010176 | V22: 52.055274 | W22: 53.118734 | X22: 54.200807 | Y22: 55.301747 | Z22: 56.42181
A23: Implied upside One-Stage | B23: =B10/B22-1 -> -0.0095286937 | D23: EPS | E23: 9.96 | F23: 13.55 | G23: 13.46 | H23: =PL!$M$65 -> 10.19 | I23: =PL!$N$65 -> 5.34 | J23: =J25/J24 -> 11.2875 | K23: =K25/K24 -> 11.851875 | L23: =L25/L24 -> 12.444469 | M23: =M25/M24 -> 13.066692 | N23: =N25/N24 -> 13.720027 | R23: =R24-0.5% -> 0.01 | S23: 50.783604 | T23: 51.836858 | U23: 52.908834 | V23: 53.999791 | W23: 55.109992 | X23: 56.2397 | Y23: 57.389183 | Z23: 58.55871
A24: Implied upside Two-Stage | B24: =(B15/B22)-1 -> 0.12236747 | D24: Payout | E24: =E25/E23 -> 0.13554217 | F24: =F25/F23 -> 0.36900369 | G24: =G25/G23 -> 0.38632987 | H24: =H25/H23 -> 0.52011776 | I24: =I25/I23 -> 0.80524345 | J24: 0.4 | K24: 0.4 | L24: 0.4 | M24: 0.4 | N24: 0.4 | R24: =R25-0.5% -> 0.015 | S24: 52.79454 | T24: 53.896838 | U24: 55.018811 | V24: 56.160732 | W24: 57.322876 | X24: 58.505522 | Y24: 59.708951 | Z24: 60.933446
A25: Implied upside H-model | B25: =B20/B22-1 -> 0.071870038 | D25: Dividends | E25: 1.35 | F25: 5 | G25: 5.2 | H25: 5.3 | I25: 4.3 | J25: =$I$25*(1+$B$13)^J22 -> 4.515 | K25: =$I$25*(1+$B$13)^K22 -> 4.74075 | L25: =$I$25*(1+$B$13)^L22 -> 4.9777875 | M25: =$I$25*(1+$B$13)^M22 -> 5.2266769 | N25: =$I$25*(1+$B$13)^N22 -> 5.4880107 | O25: =N25*(1+B17) -> 5.5977709 | R25: 0.02 | S25: 55.042481 | T25: 56.199605 | U25: 57.377468 | V25: 58.576358 | W25: 59.796568 | X25: 61.03839 | Y25: 62.302122 | Z25: 63.588064
A26: Implied growth rate by current price | B26: =B5-B7/B22 -> 0.022456312 | D26: Dividends Growth YoY | F26: =F25/E25-1 -> 2.7037037 | G26: =G25/F25-1 -> 0.04 | H26: =H25/G25-1 -> 0.019230769 | I26: =I25/H25-1 -> -0.18867925 | J26: =J25/I25-1 -> 0.05 | K26: =K25/J25-1 -> 0.05 | L26: =L25/K25-1 -> 0.05 | M26: =M25/L25-1 -> 0.05 | N26: =N25/M25-1 -> 0.05 | R26: =R25+0.5% -> 0.025 | S26: 57.571951 | T26: 58.790767 | U26: 60.031519 | V26: 61.294514 | W26: 62.580061 | X26: 63.888471 | Y26: 65.220059 | Z26: 66.575143
D27: Discount factor | J27: =(1+$B$5)^(-J22) -> 0.90510223 | K27: =(1+$B$5)^(-K22) -> 0.81921004 | L27: =(1+$B$5)^(-L22) -> 0.74146883 | M27: =(1+$B$5)^(-M22) -> 0.67110509 | N27: =(1+$B$5)^(-N22) -> 0.60741871 | R27: =R26+0.5% -> 0.03 | S27: 60.439371 | T27: 61.72812 | U27: 63.040164 | V27: 64.375828 | W27: 65.735442 | X27: 67.119336 | Y27: 68.527846 | Z27: 69.96131
D28: PV of dividends | J28: =J25*J27 -> 4.0865366 | K28: =K25*K27 -> 3.88367 | L28: =L25*L27 -> 3.6908743 | M28: =M25*M27 -> 3.5076495 | N28: =N25*N27 -> 3.3335204 | R28: =R27+0.5% -> 0.035 | S28: 63.717316 | T28: 65.086012 | U28: 66.479554 | V28: 67.898291 | W28: 69.342575 | X28: 70.812761 | Y28: 72.309206 | Z28: 73.832272
D29: Sum of PV of dividends | J29: =SUM(J28:N28) -> 18.502251 | R29: =R28+0.5% -> 0.04 | S29: 67.500746 | T29: 68.961716 | U29: 70.449324 | V29: 71.963945 | W29: 73.505957 | X29: 75.07574 | Y29: 76.67368 | Z29: 78.300165
D30: Terminal Value | N30: =O25/($B$5-$B$17) -> 65.974437 | R30: =R29+0.5% -> 0.045 | S30: 71.916354 | T30: 73.485016 | U30: 75.082408 | V30: 76.708934 | W30: 78.365003 | X30: 80.051026 | Y30: 81.76742 | Z30: 83.514604
D31: PV of Terminal Value | J31: =N30/(1+$B$5)^N22 -> 40.074107
D32: Total PV | J32: =J29+J31 -> 58.576358
D34: III. H-Model | E34: As an auxiliary model for sensitivity testing.
D36: Fact | J36: Forecast | S36: High Growth
D37: Year | E37: 2021 | F37: 2022 | G37: 2023 | H37: 2024 | I37: 2025 | J37: 2026 | K37: 2027 | L37: 2028 | M37: 2029 | N37: 2030 | O37: 2032 | R37: =$J$48 -> 55.940897 | S37: =T37-0.5% -> 0.035 | T37: =U37-0.5% -> 0.04 | U37: =V37-0.5% -> 0.045 | V37: 0.05 | W37: =V37+0.5% -> 0.055 | X37: =W37+0.5% -> 0.06 | Y37: =X37+0.5% -> 0.065 | Z37: =Y37+0.5% -> 0.07
D38: Period | I38: 0 | J38: 1 | K38: 2 | L38: 3 | M38: 4 | N38: 5 | O38: Terminal | Q38: Terminal (low) Growth | R38: =R39-0.5% -> 0.005 | S38: 46.827122 | T38: 47.439261 | U38: 48.057552 | V38: 48.682038 | W38: 49.312765 | X38: 49.949778 | Y38: 50.593122 | Z38: 51.242842
D39: EPS | E39: 9.96 | F39: 13.55 | G39: 13.46 | H39: =PL!$M$65 -> 10.19 | I39: =PL!$N$65 -> 5.34 | J39: =J41/J40 -> 11.2875 | K39: =K41/K40 -> 11.78415 | L39: =L41/L40 -> 12.231948 | M39: =M41/M40 -> 12.62337 | N39: =N41/N40 -> 12.951578 | R39: =R40-0.5% -> 0.01 | S39: 48.902807 | T39: 49.544597 | U39: 50.192855 | V39: 50.84763 | W39: 51.508968 | X39: 52.176917 | Y39: 52.851524 | Z39: 53.532838
D40: Payout | E40: =E41/E39 -> 0.13554217 | F40: =F41/F39 -> 0.36900369 | G40: =G41/G39 -> 0.38632987 | H40: =H41/H39 -> 0.52011776 | I40: =I41/I39 -> 0.80524345 | J40: 0.4 | K40: 0.4 | L40: 0.4 | M40: 0.4 | N40: 0.4 | R40: =R41-0.5% -> 0.015 | S40: 51.208404 | T40: 51.883135 | U40: 52.564689 | V40: 53.253114 | W40: 53.948461 | X40: 54.650781 | Y40: 55.360123 | Z40: 56.076538
D41: Dividends | E41: 1.35 | F41: 5 | G41: 5.2 | H41: 5.3 | I41: 4.3 | J41: =$I$25*(1+$B$18)^J38 -> 4.515 | K41: =J41*(1+$B$17+($B$18-$B$17)*($B$19-J38)/$B$19) -> 4.71366 | L41: =K41*(1+$B$17+($B$18-$B$17)*($B$19-K38)/$B$19) -> 4.8927791 | M41: =L41*(1+$B$17+($B$18-$B$17)*($B$19-L38)/$B$19) -> 5.049348 | N41: =M41*(1+$B$17+($B$18-$B$17)*($B$19-M38)/$B$19) -> 5.1806311 | O41: =N41*(1+B17) -> 5.2842437 | R41: 0.02 | S41: 53.784556 | T41: 54.496101 | U41: 55.214864 | V41: 55.940897 | W41: 56.674253 | X41: 57.414985 | Y41: 58.163146 | Z41: 58.91879
D42: Dividends Growth YoY | F42: =F41/E41-1 -> 2.7037037 | G42: =G41/F41-1 -> 0.04 | H42: =H41/G41-1 -> 0.019230769 | I42: =I41/H41-1 -> -0.18867925 | J42: =J41/I41-1 -> 0.05 | K42: =K41/J41-1 -> 0.044 | L42: =L41/K41-1 -> 0.038 | M42: =M41/L41-1 -> 0.032 | N42: =N41/M41-1 -> 0.026 | R42: =R41+0.5% -> 0.025 | S42: 56.682083 | T42: 57.435044 | U42: 58.195668 | V42: 58.964008 | W42: 59.740123 | X42: 60.524068 | Y42: 61.3159 | Z42: 62.115676
D43: Discount factor | J43: =(1+$B$5)^(-J38) -> 0.90510223 | K43: =(1+$B$5)^(-K38) -> 0.81921004 | L43: =(1+$B$5)^(-L38) -> 0.74146883 | M43: =(1+$B$5)^(-M38) -> 0.67110509 | N43: =(1+$B$5)^(-N38) -> 0.60741871 | R43: =R42+0.5% -> 0.03 | S43: 59.965389 | T43: 60.765289 | U43: 61.573355 | V43: 62.389645 | W43: 63.214221 | X43: 64.047142 | Y43: 64.888469 | Z43: 65.738263
D44: PV of dividends | J44: =J41*J43 -> 4.0865366 | K44: =K41*K43 -> 3.8614776 | L44: =L41*L43 -> 3.6278432 | M44: =M41*M43 -> 3.3886432 | N44: =N41*N43 -> 3.1468122 | R44: =R43+0.5% -> 0.035 | S44: 63.717316 | T44: 64.570864 | U44: 65.433154 | V44: 66.304248 | W44: 67.184212 | X44: 68.07311 | Y44: 68.971007 | Z44: 69.877968
D45: Sum of PV of dividends | J45: =SUM(J44:N44) -> 18.111313 | R45: =R44+0.5% -> 0.04 | S45: 68.046259 | T45: 68.961716 | U45: 69.886578 | V45: 70.820915 | W45: 71.764796 | X45: 72.718291 | Y45: 73.681469 | Z45: 74.654401
D46: Terminal Value | N46: =O41/($B$5-$B$17) -> 62.279254 | R46: =R45+0.5% -> 0.045 | S46: 73.096833 | T46: 74.08453 | U46: 75.082408 | V46: 76.090542 | W46: 77.109007 | X46: 78.137879 | Y46: 79.177233 | Z46: 80.227145
D47: PV of Terminal Value | J47: =N46/(1+$B$5)^N38 -> 37.829585
D48: Total PV | J48: =J45+J47 -> 55.940897

Sheet Results
C1: Business Valuation Method | D1: Share Value | E1: Weight | F1: Weighted estimated share value
C3: Relative Valuation | D3: ='Relative Valuation'!E19 -> 57.642307 | E3: 0.3 | F3: =E3*D3 -> 17.292692
C4: DCF (FCFF) | D4: =DCF!D47 -> 90.027527 | E4: 0.1 | F4: =E4*D4 -> 9.0027527
C5: DCF (FCFE) | D5: =DCF!D59 -> 81.969191 | E5: 0.3 | F5: =E5*D5 -> 24.590757
C6: DDM (1-step) | D6: =DDM!B10 -> 51.692697 | E6: 0.15 | F6: =E6*D6 -> 7.7539046
C7: DDM (2-step) | D7: =DDM!B15 -> 58.576358 | E7: 0.05 | F7: =E7*D7 -> 2.9288179
C8: DDM (H-model) | D8: =DDM!B20 -> 55.940897 | E8: 0.1 | F8: =E8*D8 -> 5.5940897
C9: Estimated share value | D9: =SUMPRODUCT(D3:D8,E3:E8) -> 67.163014 | F9: =SUM(F3:F8) -> 67.163014
C10: Actual (for info) | D10: =Ratios!D3 -> 52.19 | F10: =Ratios!D3 -> 52.19
C11: Implied upside | F11: =F9/F10-1 -> 0.28689431
